{
  "type": "cdl",
  "project": "cams/gkab",
  "source": "http://oracc.org/cams/gkab",
  "license": "This data is released under the CC0 license",
  "license-url": "https://creativecommons.org/publicdomain/zero/1.0/",
  "more-info": "http://oracc.org/doc/opendata/",
  "UTC-timestamp": "2017-06-21T21:51:52",
  "textid": "P348887",
  "cdl": [
    {
      "node": "c",
      "type": "text",
      "id": "P348887.U0",
      "cdl": [
        {
          "node": "d",
          "subtype": "tablet",
          "type": "tablet",
          "ref": "P348887.x147.1",
          "label": "x147"
        },
        {
          "node": "d",
          "subtype": "obverse",
          "type": "obverse",
          "ref": "P348887.o.2",
          "label": "o"
        },
        {
          "node": "d",
          "type": "nonx",
          "ref": "P348887.3",
          "strict": "1",
          "extent": "0",
          "scope": "obverse",
          "state": "missing"
        },
        {
          "node": "d",
          "subtype": "reverse",
          "type": "reverse",
          "ref": "P348887.r.4",
          "label": "r"
        },
        {
          "node": "d",
          "type": "nonx",
          "ref": "P348887.5",
          "strict": "1",
          "extent": "start",
          "scope": "reverse",
          "state": "missing"
        },
        {
          "node": "c",
          "type": "discourse",
          "subtype": "body",
          "id": "P348887.U1",
          "cdl": [
            {
              "node": "c",
              "type": "sentence",
              "id": "P348887.U2",
              "label": "r 1' - r 6'",
              "cdl": [
                {
                  "node": "d",
                  "type": "line-start",
                  "ref": "P348887.6",
                  "n": "1'",
                  "label": "r 1'"
                },
                {
                  "node": "l",
                  "frag": "x",
                  "id": "P348887.l070eb",
                  "ref": "P348887.6.1",
                  "inst": "u",
                  "f": {
                    "lang": "akk-x-ltebab",
                    "form": "x",
                    "delim": " ",
                    "gdl": [
                      {
                        "v": "x",
                        "id": "P348887.6.1.0"
                      }
                    ],
                    "pos": "u"
                  }
                },
                {
                  "node": "l",
                  "frag": "x",
                  "id": "P348887.l070ec",
                  "ref": "P348887.6.2",
                  "inst": "u",
                  "f": {
                    "lang": "akk-x-ltebab",
                    "form": "x",
                    "delim": " ",
                    "gdl": [
                      {
                        "v": "x",
                        "id": "P348887.6.2.0"
                      }
                    ],
                    "pos": "u"
                  }
                },
                {
                  "node": "l",
                  "frag": "x",
                  "id": "P348887.l070ed",
                  "ref": "P348887.6.3",
                  "inst": "u",
                  "f": {
                    "lang": "akk-x-ltebab",
                    "form": "x",
                    "delim": " ",
                    "gdl": [
                      {
                        "v": "x",
                        "id": "P348887.6.3.0"
                      }
                    ],
                    "pos": "u"
                  }
                },
                {
                  "node": "l",
                  "frag": "[...]",
                  "id": "P348887.l070ee",
                  "ref": "P348887.6.4",
                  "inst": "u",
                  "f": {
                    "lang": "akk-x-ltebab",
                    "form": "x",
                    "gdl": [
                      {
                        "x": "ellipsis",
                        "id": "P348887.6.4.0",
                        "breakStart": "1",
                        "break": "missing",
                        "o": "]",
                        "breakEnd": "P348887.6.4.0"
                      }
                    ],
                    "pos": "u"
                  }
                },
                {
                  "node": "d",
                  "type": "line-start",
                  "ref": "P348887.7",
                  "n": "2'",
                  "label": "r 2'"
                },
                {
                  "node": "l",
                  "frag": "u₂-mar-raq-ma",
                  "id": "P348887.l070ef",
                  "ref": "P348887.7.1",
                  "inst": "+marāqu[rub//clear of claims]V$umarraqma",
                  "sig": "@cams/gkab%akk-x-ltebab:u₂-mar-raq-ma=marāqu[rub//clear of claims]V'V$umarraqma",
                  "f": {
                    "lang": "akk-x-ltebab",
                    "form": "u₂-mar-raq-ma",
                    "delim": " ",
                    "gdl": [
                      {
                        "v": "u₂",
                        "id": "P348887.7.1.0",
                        "delim": "-"
                      },
                      {
                        "v": "mar",
                        "id": "P348887.7.1.1",
                        "delim": "-"
                      },
                      {
                        "v": "raq",
                        "id": "P348887.7.1.2",
                        "delim": "-"
                      },
                      {
                        "v": "ma",
                        "id": "P348887.7.1.3"
                      }
                    ],
                    "cf": "marāqu",
                    "gw": "rub",
                    "sense": "clear of claims",
                    "norm": "umarraqma",
                    "pos": "V",
                    "epos": "V"
                  }
                },
                {
                  "node": "l",
                  "frag": "a-na",
                  "id": "P348887.l070f0",
                  "ref": "P348887.7.2",
                  "inst": "ana[to//for]",
                  "sig": "@cams/gkab%akk-x-ltebab:a-na=ana[to//for]PRP'PRP$ana",
                  "f": {
                    "lang": "akk-x-ltebab",
                    "form": "a-na",
                    "delim": " ",
                    "gdl": [
                      {
                        "v": "a",
                        "id": "P348887.7.2.0",
                        "delim": "-"
                      },
                      {
                        "v": "na",
                        "id": "P348887.7.2.1"
                      }
                    ],
                    "cf": "ana",
                    "gw": "to",
                    "sense": "for",
                    "norm": "ana",
                    "pos": "PRP",
                    "epos": "PRP"
                  }
                },
                {
                  "node": "l",
                  "frag": "{m}{d}INANA-x-x",
                  "id": "P348887.l070f1",
                  "ref": "P348887.7.3",
                  "inst": "u",
                  "f": {
                    "lang": "akk-x-ltebab",
                    "form": "{m}{d}INANA-x-x",
                    "delim": " ",
                    "gdl": [
                      {
                        "det": "semantic",
                        "pos": "pre",
                        "seq": [
                          {
                            "v": "m",
                            "id": "P348887.7.3.0"
                          }
                        ]
                      },
                      {
                        "det": "semantic",
                        "pos": "pre",
                        "seq": [
                          {
                            "v": "d",
                            "id": "P348887.7.3.1"
                          }
                        ]
                      },
                      {
                        "s": "INANA",
                        "id": "P348887.7.3.2",
                        "role": "logo",
                        "logolang": "sux",
                        "delim": "--",
                        "gdl_em": "1"
                      },
                      {
                        "v": "x",
                        "id": "P348887.7.3.3",
                        "delim": "-"
                      },
                      {
                        "v": "x",
                        "id": "P348887.7.3.4"
                      }
                    ],
                    "pos": "u"
                  }
                },
                {
                  "node": "l",
                  "frag": "⸢DUMU⸣",
                  "id": "P348887.l070f2",
                  "ref": "P348887.7.4",
                  "inst": "māru[son]",
                  "sig": "@cams/gkab%akk-x-ltebab:DUMU=māru[son//son]N'N$māru",
                  "f": {
                    "lang": "akk-x-ltebab",
                    "form": "DUMU",
                    "delim": " ",
                    "gdl": [
                      {
                        "s": "DUMU",
                        "id": "P348887.7.4.0",
                        "break": "damaged",
                        "queried": "1",
                        "ho": "1",
                        "role": "logo",
                        "logolang": "sux",
                        "hc": "1"
                      }
                    ],
                    "cf": "māru",
                    "gw": "son",
                    "sense": "son",
                    "norm": "māru",
                    "pos": "N",
                    "epos": "N"
                  }
                },
                {
                  "node": "l",
                  "frag": "[...]",
                  "id": "P348887.l070f3",
                  "ref": "P348887.7.5",
                  "inst": "u",
                  "f": {
                    "lang": "akk-x-ltebab",
                    "form": "x",
                    "gdl": [
                      {
                        "x": "ellipsis",
                        "id": "P348887.7.5.0",
                        "breakStart": "1",
                        "break": "missing",
                        "o": "]",
                        "breakEnd": "P348887.7.5.0"
                      }
                    ],
                    "pos": "u"
                  }
                },
                {
                  "node": "d",
                  "type": "line-start",
                  "ref": "P348887.8",
                  "n": "3'",
                  "label": "r 3'"
                },
                {
                  "node": "l",
                  "frag": "{lu₂}mu-kin₇",
                  "id": "P348887.l070f4",
                  "ref": "P348887.8.1",
                  "inst": "mukīn[witness]",
                  "sig": "@cams/gkab%akk-x-ltebab:{lu₂}mu-kin₇=mukinnu[witness//witness]N'N$mukīn",
                  "f": {
                    "lang": "akk-x-ltebab",
                    "form": "{lu₂}mu-kin₇",
                    "delim": " ",
                    "gdl": [
                      {
                        "det": "semantic",
                        "pos": "pre",
                        "seq": [
                          {
                            "v": "lu₂",
                            "id": "P348887.8.1.0"
                          }
                        ]
                      },
                      {
                        "v": "mu",
                        "id": "P348887.8.1.1",
                        "delim": "-"
                      },
                      {
                        "v": "kin₇",
                        "id": "P348887.8.1.2"
                      }
                    ],
                    "cf": "mukinnu",
                    "gw": "witness",
                    "sense": "witness",
                    "norm": "mukīn",
                    "pos": "N",
                    "epos": "N"
                  }
                },
                {
                  "node": "l",
                  "frag": "{m}ha-an-nin-an-e",
                  "id": "P348887.l070f5",
                  "ref": "P348887.8.2",
                  "inst": "+Hanninane[1]PN$",
                  "sig": "@cams/gkab%akk-x-ltebab:{m}ha-an-nin-an-e=Hanninane[1//1]PN'PN$Hanninane",
                  "f": {
                    "lang": "akk-x-ltebab",
                    "form": "{m}ha-an-nin-an-e",
                    "delim": " ",
                    "gdl": [
                      {
                        "det": "semantic",
                        "pos": "pre",
                        "seq": [
                          {
                            "v": "m",
                            "id": "P348887.8.2.0"
                          }
                        ]
                      },
                      {
                        "v": "ha",
                        "id": "P348887.8.2.1",
                        "delim": "-"
                      },
                      {
                        "v": "an",
                        "id": "P348887.8.2.2",
                        "delim": "-"
                      },
                      {
                        "v": "nin",
                        "id": "P348887.8.2.3",
                        "delim": "-"
                      },
                      {
                        "v": "an",
                        "id": "P348887.8.2.4",
                        "delim": "-"
                      },
                      {
                        "v": "e",
                        "id": "P348887.8.2.5"
                      }
                    ],
                    "cf": "Hanninane",
                    "gw": "1",
                    "sense": "1",
                    "norm": "Hanninane",
                    "pos": "PN",
                    "epos": "PN"
                  }
                },
                {
                  "node": "l",
                  "frag": "⸢DUMU⸣",
                  "id": "P348887.l070f6",
                  "ref": "P348887.8.3",
                  "inst": "māru[son]",
                  "sig": "@cams/gkab%akk-x-ltebab:DUMU=māru[son//son]N'N$māru",
                  "f": {
                    "lang": "akk-x-ltebab",
                    "form": "DUMU",
                    "delim": " ",
                    "gdl": [
                      {
                        "s": "DUMU",
                        "id": "P348887.8.3.0",
                        "break": "damaged",
                        "queried": "1",
                        "ho": "1",
                        "role": "logo",
                        "logolang": "sux",
                        "hc": "1"
                      }
                    ],
                    "cf": "māru",
                    "gw": "son",
                    "sense": "son",
                    "norm": "māru",
                    "pos": "N",
                    "epos": "N"
                  }
                },
                {
                  "node": "l",
                  "frag": "x",
                  "id": "P348887.l070f7",
                  "ref": "P348887.8.4",
                  "inst": "u",
                  "f": {
                    "lang": "akk-x-ltebab",
                    "form": "x",
                    "delim": " ",
                    "gdl": [
                      {
                        "v": "x",
                        "id": "P348887.8.4.0"
                      }
                    ],
                    "pos": "u"
                  }
                },
                {
                  "node": "l",
                  "frag": "[...]",
                  "id": "P348887.l070f8",
                  "ref": "P348887.8.5",
                  "inst": "u",
                  "f": {
                    "lang": "akk-x-ltebab",
                    "form": "x",
                    "gdl": [
                      {
                        "x": "ellipsis",
                        "id": "P348887.8.5.0",
                        "breakStart": "1",
                        "break": "missing",
                        "o": "]",
                        "breakEnd": "P348887.8.5.0"
                      }
                    ],
                    "pos": "u"
                  }
                },
                {
                  "node": "d",
                  "type": "line-start",
                  "ref": "P348887.9",
                  "n": "4'",
                  "label": "r 4'"
                },
                {
                  "node": "l",
                  "frag": "{m}{d}60--NUMUN-MU",
                  "id": "P348887.l070f9",
                  "ref": "P348887.9.1",
                  "inst": "Anu-zer-iddin[1]",
                  "sig": "@cams/gkab%akk-x-ltebab:{m}{d}60-NUMUN-MU=Anu-zer-iddin[1//1]PN'PN$Anu-zer-iddin",
                  "f": {
                    "lang": "akk-x-ltebab",
                    "form": "{m}{d}60-NUMUN-MU",
                    "delim": " ",
                    "gdl": [
                      {
                        "det": "semantic",
                        "pos": "pre",
                        "seq": [
                          {
                            "v": "m",
                            "id": "P348887.9.1.0"
                          }
                        ]
                      },
                      {
                        "det": "semantic",
                        "pos": "pre",
                        "seq": [
                          {
                            "v": "d",
                            "id": "P348887.9.1.1"
                          }
                        ]
                      },
                      {
                        "n": "n",
                        "sexified": "1(geš₂)",
                        "form": "60",
                        "id": "P348887.9.1.2",
                        "delim": "--",
                        "gdl_em": "1",
                        "seq": [
                          {
                            "r": "60"
                          }
                        ]
                      },
                      {
                        "s": "NUMUN",
                        "id": "P348887.9.1.3",
                        "role": "logo",
                        "logolang": "sux",
                        "delim": "--",
                        "gdl_em": "1"
                      },
                      {
                        "s": "MU",
                        "id": "P348887.9.1.4",
                        "role": "logo",
                        "logolang": "sux"
                      }
                    ],
                    "cf": "Anu-zer-iddin",
                    "gw": "1",
                    "sense": "1",
                    "norm": "Anu-zer-iddin",
                    "pos": "PN",
                    "epos": "PN"
                  }
                },
                {
                  "node": "l",
                  "frag": "DUMU",
                  "id": "P348887.l070fa",
                  "ref": "P348887.9.2",
                  "inst": "māru[son]",
                  "sig": "@cams/gkab%akk-x-ltebab:DUMU=māru[son//son]N'N$māru",
                  "f": {
                    "lang": "akk-x-ltebab",
                    "form": "DUMU",
                    "delim": " ",
                    "gdl": [
                      {
                        "s": "DUMU",
                        "id": "P348887.9.2.0",
                        "role": "logo",
                        "logolang": "sux"
                      }
                    ],
                    "cf": "māru",
                    "gw": "son",
                    "sense": "son",
                    "norm": "māru",
                    "pos": "N",
                    "epos": "N"
                  }
                },
                {
                  "node": "l",
                  "frag": "ša₂",
                  "id": "P348887.l070fb",
                  "ref": "P348887.9.3",
                  "inst": "ša[of]DET$",
                  "sig": "@cams/gkab%akk-x-ltebab:ša₂=ša[of//of]DET'DET$ša",
                  "f": {
                    "lang": "akk-x-ltebab",
                    "form": "ša₂",
                    "delim": " ",
                    "gdl": [
                      {
                        "v": "ša₂",
                        "id": "P348887.9.3.0"
                      }
                    ],
                    "cf": "ša",
                    "gw": "of",
                    "sense": "of",
                    "norm": "ša",
                    "pos": "DET",
                    "epos": "DET"
                  }
                },
                {
                  "node": "l",
                  "frag": "{m}da-la-x",
                  "id": "P348887.l070fc",
                  "ref": "P348887.9.4",
                  "inst": "u",
                  "f": {
                    "lang": "akk-x-ltebab",
                    "form": "{m}da-la-x",
                    "delim": " ",
                    "gdl": [
                      {
                        "det": "semantic",
                        "pos": "pre",
                        "seq": [
                          {
                            "v": "m",
                            "id": "P348887.9.4.0"
                          }
                        ]
                      },
                      {
                        "v": "da",
                        "id": "P348887.9.4.1",
                        "delim": "-"
                      },
                      {
                        "v": "la",
                        "id": "P348887.9.4.2",
                        "delim": "-"
                      },
                      {
                        "v": "x",
                        "id": "P348887.9.4.3"
                      }
                    ],
                    "pos": "u"
                  }
                },
                {
                  "node": "l",
                  "frag": "[...]",
                  "id": "P348887.l070fd",
                  "ref": "P348887.9.5",
                  "inst": "u",
                  "f": {
                    "lang": "akk-x-ltebab",
                    "form": "x",
                    "gdl": [
                      {
                        "x": "ellipsis",
                        "id": "P348887.9.5.0",
                        "breakStart": "1",
                        "break": "missing",
                        "o": "]",
                        "breakEnd": "P348887.9.5.0"
                      }
                    ],
                    "pos": "u"
                  }
                },
                {
                  "node": "d",
                  "type": "line-start",
                  "ref": "P348887.10",
                  "n": "5'",
                  "label": "r 5'"
                },
                {
                  "node": "l",
                  "frag": "{m}{d}60--ŠEŠ-MU{nu}",
                  "id": "P348887.l070fe",
                  "ref": "P348887.10.1",
                  "inst": "Anu-ah-ittannu[1]",
                  "sig": "@cams/gkab%akk-x-ltebab:{m}{d}60-ŠEŠ-MU{+nu}=Anu-ah-ittannu[1//1]PN'PN$Anu-ah-ittannu",
                  "f": {
                    "lang": "akk-x-ltebab",
                    "form": "{m}{d}60-ŠEŠ-MU{+nu}",
                    "delim": " ",
                    "gdl": [
                      {
                        "det": "semantic",
                        "pos": "pre",
                        "seq": [
                          {
                            "v": "m",
                            "id": "P348887.10.1.0"
                          }
                        ]
                      },
                      {
                        "det": "semantic",
                        "pos": "pre",
                        "seq": [
                          {
                            "v": "d",
                            "id": "P348887.10.1.1"
                          }
                        ]
                      },
                      {
                        "n": "n",
                        "sexified": "1(geš₂)",
                        "form": "60",
                        "id": "P348887.10.1.2",
                        "delim": "--",
                        "gdl_em": "1",
                        "seq": [
                          {
                            "r": "60"
                          }
                        ]
                      },
                      {
                        "s": "ŠEŠ",
                        "id": "P348887.10.1.3",
                        "role": "logo",
                        "logolang": "sux",
                        "delim": "--",
                        "gdl_em": "1"
                      },
                      {
                        "s": "MU",
                        "id": "P348887.10.1.4",
                        "role": "logo",
                        "logolang": "sux"
                      },
                      {
                        "det": "phonetic",
                        "pos": "post",
                        "seq": [
                          {
                            "v": "nu",
                            "id": "P348887.10.1.5"
                          }
                        ]
                      }
                    ],
                    "cf": "Anu-ah-ittannu",
                    "gw": "1",
                    "sense": "1",
                    "norm": "Anu-ah-ittannu",
                    "pos": "PN",
                    "epos": "PN"
                  }
                },
                {
                  "node": "l",
                  "frag": "DUMU",
                  "id": "P348887.l070ff",
                  "ref": "P348887.10.2",
                  "inst": "+māru[son]N$mār",
                  "sig": "@cams/gkab%akk-x-ltebab:DUMU=māru[son//son]N'N$mār",
                  "f": {
                    "lang": "akk-x-ltebab",
                    "form": "DUMU",
                    "delim": " ",
                    "gdl": [
                      {
                        "s": "DUMU",
                        "id": "P348887.10.2.0",
                        "role": "logo",
                        "logolang": "sux"
                      }
                    ],
                    "cf": "māru",
                    "gw": "son",
                    "sense": "son",
                    "norm": "mār",
                    "pos": "N",
                    "epos": "N"
                  }
                },
                {
                  "node": "l",
                  "frag": "{m}bi-⸢be₂⸣-[e-a]",
                  "id": "P348887.l07100",
                  "ref": "P348887.10.3",
                  "inst": "+Bibea[1]PN$",
                  "sig": "@cams/gkab%akk-x-ltebab:{m}bi-be₂-e-a=Bibea[1//1]PN'PN$Bibea",
                  "f": {
                    "lang": "akk-x-ltebab",
                    "form": "{m}bi-be₂-e-a",
                    "gdl": [
                      {
                        "det": "semantic",
                        "pos": "pre",
                        "seq": [
                          {
                            "v": "m",
                            "id": "P348887.10.3.0"
                          }
                        ]
                      },
                      {
                        "v": "bi",
                        "id": "P348887.10.3.1",
                        "delim": "-"
                      },
                      {
                        "v": "be₂",
                        "id": "P348887.10.3.2",
                        "break": "damaged",
                        "ho": "1",
                        "delim": "-",
                        "hc": "1"
                      },
                      {
                        "v": "e",
                        "id": "P348887.10.3.3",
                        "breakStart": "1",
                        "o": "[",
                        "break": "missing",
                        "delim": "-"
                      },
                      {
                        "v": "a",
                        "id": "P348887.10.3.4",
                        "break": "missing",
                        "o": "]",
                        "breakEnd": "P348887.10.3.3"
                      }
                    ],
                    "cf": "Bibea",
                    "gw": "1",
                    "sense": "1",
                    "norm": "Bibea",
                    "pos": "PN",
                    "epos": "PN"
                  }
                },
                {
                  "node": "d",
                  "type": "line-start",
                  "ref": "P348887.11",
                  "n": "6'",
                  "label": "r 6'"
                },
                {
                  "node": "l",
                  "frag": "{⸢m⸣}{d}60--⸢GI⸣",
                  "id": "P348887.l07101",
                  "ref": "P348887.11.1",
                  "inst": "Anu-mušallim[1]",
                  "sig": "@cams/gkab%akk-x-ltebab:{m}{d}60-GI=Anu-mušallim[1//1]PN'PN$Anu-mušallim",
                  "f": {
                    "lang": "akk-x-ltebab",
                    "form": "{m}{d}60-GI",
                    "delim": " ",
                    "gdl": [
                      {
                        "det": "semantic",
                        "pos": "pre",
                        "seq": [
                          {
                            "v": "m",
                            "id": "P348887.11.1.0",
                            "break": "damaged",
                            "ho": "1",
                            "hc": "1"
                          }
                        ]
                      },
                      {
                        "det": "semantic",
                        "pos": "pre",
                        "seq": [
                          {
                            "v": "d",
                            "id": "P348887.11.1.1"
                          }
                        ]
                      },
                      {
                        "n": "n",
                        "sexified": "1(geš₂)",
                        "form": "60",
                        "id": "P348887.11.1.2",
                        "delim": "--",
                        "gdl_em": "1",
                        "seq": [
                          {
                            "r": "60"
                          }
                        ]
                      },
                      {
                        "s": "GI",
                        "id": "P348887.11.1.3",
                        "break": "damaged",
                        "ho": "1",
                        "role": "logo",
                        "logolang": "sux",
                        "hc": "1"
                      }
                    ],
                    "cf": "Anu-mušallim",
                    "gw": "1",
                    "sense": "1",
                    "norm": "Anu-mušallim",
                    "pos": "PN",
                    "epos": "PN"
                  }
                },
                {
                  "node": "l",
                  "frag": "[...]",
                  "id": "P348887.l07102",
                  "ref": "P348887.11.2",
                  "inst": "u",
                  "f": {
                    "lang": "akk-x-ltebab",
                    "form": "x",
                    "gdl": [
                      {
                        "x": "ellipsis",
                        "id": "P348887.11.2.0",
                        "breakStart": "1",
                        "break": "missing",
                        "o": "]",
                        "breakEnd": "P348887.11.2.0"
                      }
                    ],
                    "pos": "u"
                  }
                },
                {
                  "node": "d",
                  "type": "nonx",
                  "ref": "P348887.12",
                  "strict": "1",
                  "extent": "end",
                  "scope": "reverse",
                  "state": "missing"
                }
              ]
            }
          ]
        }
      ]
    }
  ]
}
