{
  "type": "glossary",
  "project": "rinap/rinap4",
  "source": "http://oracc.org/rinap/rinap4",
  "license": "This data is released under the CC0 license",
  "license-url": "https://creativecommons.org/publicdomain/zero/1.0/",
  "more-info": "http://oracc.org/doc/opendata/",
  "UTC-timestamp": "2017-06-21T23:03:22",
  "lang": "qpn-x-temple",
  "entries": [
    {
      "headword": "Eanna[1]TN",
      "id": "qpn-x-temple.x000003",
      "icount": "15",
      "ipct": "100",
      "xis": "qpn.r00000",
      "cf": "Eanna",
      "gw": "1",
      "pos": "TN",
      "forms": [
        {
          "type": "form",
          "id": "qpn-x-temple.x000027",
          "n": "e₂-an-na",
          "icount": "15",
          "ipct": "100",
          "xis": "qpn.r00000"
        }
      ],
      "norms": [
        {
          "id": "qpn-x-temple.x000028",
          "icount": "15",
          "ipct": "100",
          "xis": "qpn.r00000",
          "n": "Eanna",
          "forms": [
            {
              "type": "normform",
              "id": "qpn-x-temple.x000029",
              "ref": "qpn-x-temple.x000027",
              "icount": "15",
              "ipct": "100",
              "xis": "qpn.r00000"
            }
          ]
        }
      ],
      "senses": [
        {
          "type": "sense",
          "id": "qpn-x-temple.x000030",
          "n": "Eanna[1//1]TN'TN",
          "icount": "15",
          "ipct": "100",
          "xis": "qpn.r00000",
          "pos": "TN",
          "mng": "1",
          "forms": [
            {
              "type": "form",
              "id": "qpn-x-temple.x000031",
              "n": "e₂-an-na",
              "icount": "15",
              "ipct": "100",
              "xis": "qpn.r00000"
            }
          ],
          "norms": [
            {
              "id": "qpn-x-temple.x000032",
              "n": "Eanna",
              "icount": "15",
              "ipct": "100",
              "xis": "qpn.r00000"
            }
          ],
          "sigs": [
            {
              "type": "sig",
              "id": "qpn-x-temple.x000033",
              "sig": "@rinap/rinap4%akk:e₂-an-na=Eanna[1//1]TN'TN$Eanna",
              "icount": "15",
              "ipct": "100",
              "xis": "qpn.r00000"
            }
          ]
        }
      ]
    },
    {
      "headword": "Ebaradurgara[1]TN",
      "id": "qpn-x-temple.x000004",
      "icount": "3",
      "ipct": "100",
      "xis": "qpn.r00001",
      "cf": "Ebaradurgara",
      "gw": "1",
      "pos": "TN",
      "forms": [
        {
          "type": "form",
          "id": "qpn-x-temple.x000034",
          "n": "e₂-bara₂-dur₂-gar-ra",
          "icount": "3",
          "ipct": "100",
          "xis": "qpn.r00001"
        }
      ],
      "norms": [
        {
          "id": "qpn-x-temple.x000035",
          "icount": "3",
          "ipct": "100",
          "xis": "qpn.r00001",
          "n": "Ebaradurgara",
          "forms": [
            {
              "type": "normform",
              "id": "qpn-x-temple.x000036",
              "ref": "qpn-x-temple.x000034",
              "icount": "3",
              "ipct": "100",
              "xis": "qpn.r00001"
            }
          ]
        }
      ],
      "senses": [
        {
          "type": "sense",
          "id": "qpn-x-temple.x000037",
          "n": "Ebaradurgara[1//1]TN'TN",
          "icount": "3",
          "ipct": "100",
          "xis": "qpn.r00001",
          "pos": "TN",
          "mng": "1",
          "forms": [
            {
              "type": "form",
              "id": "qpn-x-temple.x000038",
              "n": "e₂-bara₂-dur₂-gar-ra",
              "icount": "3",
              "ipct": "100",
              "xis": "qpn.r00001"
            }
          ],
          "norms": [
            {
              "id": "qpn-x-temple.x000039",
              "n": "Ebaradurgara",
              "icount": "3",
              "ipct": "100",
              "xis": "qpn.r00001"
            }
          ],
          "sigs": [
            {
              "type": "sig",
              "id": "qpn-x-temple.x000040",
              "sig": "@rinap/rinap4%akk:e₂-bara₂-dur₂-gar-ra=Ebaradurgara[1//1]TN'TN$Ebaradurgara",
              "icount": "3",
              "ipct": "100",
              "xis": "qpn.r00001"
            }
          ]
        }
      ]
    },
    {
      "headword": "Edadihegal[1]TN",
      "id": "qpn-x-temple.x000001",
      "icount": "1",
      "ipct": "100",
      "xis": "qpn.r00002",
      "cf": "Edadihegal",
      "gw": "1",
      "pos": "TN",
      "forms": [
        {
          "type": "form",
          "id": "qpn-x-temple.x000041",
          "n": "a-de₂-di-he₂-gal₂",
          "icount": "1",
          "ipct": "100",
          "xis": "qpn.r00002"
        }
      ],
      "norms": [
        {
          "id": "qpn-x-temple.x000042",
          "icount": "1",
          "ipct": "100",
          "xis": "qpn.r00002",
          "n": "Adedihegal",
          "forms": [
            {
              "type": "normform",
              "id": "qpn-x-temple.x000043",
              "ref": "qpn-x-temple.x000041",
              "icount": "1",
              "ipct": "100",
              "xis": "qpn.r00002"
            }
          ]
        }
      ],
      "senses": [
        {
          "type": "sense",
          "id": "qpn-x-temple.x000044",
          "n": "Edadihegal[1//1]TN'TN",
          "icount": "1",
          "ipct": "100",
          "xis": "qpn.r00002",
          "pos": "TN",
          "mng": "1",
          "forms": [
            {
              "type": "form",
              "id": "qpn-x-temple.x000045",
              "n": "a-de₂-di-he₂-gal₂",
              "icount": "1",
              "ipct": "100",
              "xis": "qpn.r00002"
            }
          ],
          "norms": [
            {
              "id": "qpn-x-temple.x000046",
              "n": "Adedihegal",
              "icount": "1",
              "ipct": "100",
              "xis": "qpn.r00002"
            }
          ],
          "sigs": [
            {
              "type": "sig",
              "id": "qpn-x-temple.x000047",
              "sig": "@rinap/rinap4%akk:a-de₂-di-he₂-gal₂=Edadihegal[1//1]TN'TN$Adedihegal",
              "icount": "1",
              "ipct": "100",
              "xis": "qpn.r00002"
            }
          ]
        }
      ]
    },
    {
      "headword": "Edimgalkalama[1]TN",
      "id": "qpn-x-temple.x000005",
      "icount": "4",
      "ipct": "100",
      "xis": "qpn.r00003",
      "cf": "Edimgalkalama",
      "gw": "1",
      "pos": "TN",
      "forms": [
        {
          "type": "form",
          "id": "qpn-x-temple.x000048",
          "n": "e₂-dim-gal-kalam-ma",
          "icount": "4",
          "ipct": "100",
          "xis": "qpn.r00003"
        }
      ],
      "norms": [
        {
          "id": "qpn-x-temple.x000049",
          "icount": "4",
          "ipct": "100",
          "xis": "qpn.r00003",
          "n": "Edimgalkalama",
          "forms": [
            {
              "type": "normform",
              "id": "qpn-x-temple.x000050",
              "ref": "qpn-x-temple.x000048",
              "icount": "4",
              "ipct": "100",
              "xis": "qpn.r00003"
            }
          ]
        }
      ],
      "senses": [
        {
          "type": "sense",
          "id": "qpn-x-temple.x000051",
          "n": "Edimgalkalama[1//1]TN'TN",
          "icount": "4",
          "ipct": "100",
          "xis": "qpn.r00003",
          "pos": "TN",
          "mng": "1",
          "forms": [
            {
              "type": "form",
              "id": "qpn-x-temple.x000052",
              "n": "e₂-dim-gal-kalam-ma",
              "icount": "4",
              "ipct": "100",
              "xis": "qpn.r00003"
            }
          ],
          "norms": [
            {
              "id": "qpn-x-temple.x000053",
              "n": "Edimgalkalama",
              "icount": "4",
              "ipct": "100",
              "xis": "qpn.r00003"
            }
          ],
          "sigs": [
            {
              "type": "sig",
              "id": "qpn-x-temple.x000054",
              "sig": "@rinap/rinap4%akk:e₂-dim-gal-kalam-ma=Edimgalkalama[1//1]TN'TN$Edimgalkalama",
              "icount": "4",
              "ipct": "100",
              "xis": "qpn.r00003"
            }
          ]
        }
      ]
    },
    {
      "headword": "Edurgina[1]TN",
      "id": "qpn-x-temple.x000006",
      "icount": "1",
      "ipct": "100",
      "xis": "qpn.r00004",
      "cf": "Edurgina",
      "gw": "1",
      "pos": "TN",
      "forms": [
        {
          "type": "form",
          "id": "qpn-x-temple.x000055",
          "n": "e₂-dur₂-gi-na",
          "icount": "1",
          "ipct": "100",
          "xis": "qpn.r00004"
        }
      ],
      "norms": [
        {
          "id": "qpn-x-temple.x000056",
          "icount": "1",
          "ipct": "100",
          "xis": "qpn.r00004",
          "n": "Edurgina",
          "forms": [
            {
              "type": "normform",
              "id": "qpn-x-temple.x000057",
              "ref": "qpn-x-temple.x000055",
              "icount": "1",
              "ipct": "100",
              "xis": "qpn.r00004"
            }
          ]
        }
      ],
      "senses": [
        {
          "type": "sense",
          "id": "qpn-x-temple.x000058",
          "n": "Edurgina[1//1]TN'TN",
          "icount": "1",
          "ipct": "100",
          "xis": "qpn.r00004",
          "pos": "TN",
          "mng": "1",
          "forms": [
            {
              "type": "form",
              "id": "qpn-x-temple.x000059",
              "n": "e₂-dur₂-gi-na",
              "icount": "1",
              "ipct": "100",
              "xis": "qpn.r00004"
            }
          ],
          "norms": [
            {
              "id": "qpn-x-temple.x000060",
              "n": "Edurgina",
              "icount": "1",
              "ipct": "100",
              "xis": "qpn.r00004"
            }
          ],
          "sigs": [
            {
              "type": "sig",
              "id": "qpn-x-temple.x000061",
              "sig": "@rinap/rinap4%akk:e₂-dur₂-gi-na=Edurgina[1//1]TN'TN$Edurgina",
              "icount": "1",
              "ipct": "100",
              "xis": "qpn.r00004"
            }
          ]
        }
      ]
    },
    {
      "headword": "Egašankalama[1]TN",
      "id": "qpn-x-temple.x000007",
      "icount": "5",
      "ipct": "100",
      "xis": "qpn.r00005",
      "cf": "Egašankalama",
      "gw": "1",
      "pos": "TN",
      "forms": [
        {
          "type": "form",
          "id": "qpn-x-temple.x000062",
          "n": "e₂-gašan-kalam-ma",
          "icount": "5",
          "ipct": "100",
          "xis": "qpn.r00005"
        }
      ],
      "norms": [
        {
          "id": "qpn-x-temple.x000063",
          "icount": "5",
          "ipct": "100",
          "xis": "qpn.r00005",
          "n": "Egašankalama",
          "forms": [
            {
              "type": "normform",
              "id": "qpn-x-temple.x000064",
              "ref": "qpn-x-temple.x000062",
              "icount": "5",
              "ipct": "100",
              "xis": "qpn.r00005"
            }
          ]
        }
      ],
      "senses": [
        {
          "type": "sense",
          "id": "qpn-x-temple.x000065",
          "n": "Egašankalama[1//1]TN'TN",
          "icount": "5",
          "ipct": "100",
          "xis": "qpn.r00005",
          "pos": "TN",
          "mng": "1",
          "forms": [
            {
              "type": "form",
              "id": "qpn-x-temple.x000066",
              "n": "e₂-gašan-kalam-ma",
              "icount": "5",
              "ipct": "100",
              "xis": "qpn.r00005"
            }
          ],
          "norms": [
            {
              "id": "qpn-x-temple.x000067",
              "n": "Egašankalama",
              "icount": "5",
              "ipct": "100",
              "xis": "qpn.r00005"
            }
          ],
          "sigs": [
            {
              "type": "sig",
              "id": "qpn-x-temple.x000068",
              "sig": "@rinap/rinap4%akk:e₂-gašan-kalam-ma=Egašankalama[1//1]TN'TN$Egašankalama",
              "icount": "5",
              "ipct": "100",
              "xis": "qpn.r00005"
            }
          ]
        }
      ]
    },
    {
      "headword": "Egišhurankia[1]TN",
      "id": "qpn-x-temple.x000008",
      "icount": "2",
      "ipct": "100",
      "xis": "qpn.r00006",
      "cf": "Egišhurankia",
      "gw": "1",
      "pos": "TN",
      "forms": [
        {
          "type": "form",
          "id": "qpn-x-temple.x000069",
          "n": "e₂-giš-hur-an-ki-a",
          "icount": "2",
          "ipct": "100",
          "xis": "qpn.r00006"
        }
      ],
      "norms": [
        {
          "id": "qpn-x-temple.x000070",
          "icount": "2",
          "ipct": "100",
          "xis": "qpn.r00006",
          "n": "Egišhurankia",
          "forms": [
            {
              "type": "normform",
              "id": "qpn-x-temple.x000071",
              "ref": "qpn-x-temple.x000069",
              "icount": "2",
              "ipct": "100",
              "xis": "qpn.r00006"
            }
          ]
        }
      ],
      "senses": [
        {
          "type": "sense",
          "id": "qpn-x-temple.x000072",
          "n": "Egišhurankia[1//1]TN'TN",
          "icount": "2",
          "ipct": "100",
          "xis": "qpn.r00006",
          "pos": "TN",
          "mng": "1",
          "forms": [
            {
              "type": "form",
              "id": "qpn-x-temple.x000073",
              "n": "e₂-giš-hur-an-ki-a",
              "icount": "2",
              "ipct": "100",
              "xis": "qpn.r00006"
            }
          ],
          "norms": [
            {
              "id": "qpn-x-temple.x000074",
              "n": "Egišhurankia",
              "icount": "2",
              "ipct": "100",
              "xis": "qpn.r00006"
            }
          ],
          "sigs": [
            {
              "type": "sig",
              "id": "qpn-x-temple.x000075",
              "sig": "@rinap/rinap4%akk:e₂-giš-hur-an-ki-a=Egišhurankia[1//1]TN'TN$Egišhurankia",
              "icount": "2",
              "ipct": "100",
              "xis": "qpn.r00006"
            }
          ]
        }
      ]
    },
    {
      "headword": "Ehiliana[1]TN",
      "id": "qpn-x-temple.x000009",
      "icount": "3",
      "ipct": "100",
      "xis": "qpn.r00007",
      "cf": "Ehiliana",
      "gw": "1",
      "pos": "TN",
      "forms": [
        {
          "type": "form",
          "id": "qpn-x-temple.x000076",
          "n": "e₂-hi-li-an-na",
          "icount": "3",
          "ipct": "100",
          "xis": "qpn.r00007"
        }
      ],
      "norms": [
        {
          "id": "qpn-x-temple.x000077",
          "icount": "3",
          "ipct": "100",
          "xis": "qpn.r00007",
          "n": "Ehiliana",
          "forms": [
            {
              "type": "normform",
              "id": "qpn-x-temple.x000078",
              "ref": "qpn-x-temple.x000076",
              "icount": "3",
              "ipct": "100",
              "xis": "qpn.r00007"
            }
          ]
        }
      ],
      "senses": [
        {
          "type": "sense",
          "id": "qpn-x-temple.x000079",
          "n": "Ehiliana[1//1]TN'TN",
          "icount": "3",
          "ipct": "100",
          "xis": "qpn.r00007",
          "pos": "TN",
          "mng": "1",
          "forms": [
            {
              "type": "form",
              "id": "qpn-x-temple.x000080",
              "n": "e₂-hi-li-an-na",
              "icount": "3",
              "ipct": "100",
              "xis": "qpn.r00007"
            }
          ],
          "norms": [
            {
              "id": "qpn-x-temple.x000081",
              "n": "Ehiliana",
              "icount": "3",
              "ipct": "100",
              "xis": "qpn.r00007"
            }
          ],
          "sigs": [
            {
              "type": "sig",
              "id": "qpn-x-temple.x000082",
              "sig": "@rinap/rinap4%akk:e₂-hi-li-an-na=Ehiliana[1//1]TN'TN$Ehiliana",
              "icount": "3",
              "ipct": "100",
              "xis": "qpn.r00007"
            }
          ]
        }
      ]
    },
    {
      "headword": "Ehulhul[1]TN",
      "id": "qpn-x-temple.x000010",
      "icount": "1",
      "ipct": "100",
      "xis": "qpn.r00008",
      "cf": "Ehulhul",
      "gw": "1",
      "pos": "TN",
      "forms": [
        {
          "type": "form",
          "id": "qpn-x-temple.x000083",
          "n": "e₂-hul₂-hul₂",
          "icount": "1",
          "ipct": "100",
          "xis": "qpn.r00008"
        }
      ],
      "norms": [
        {
          "id": "qpn-x-temple.x000084",
          "icount": "1",
          "ipct": "100",
          "xis": "qpn.r00008",
          "n": "Ehulhul",
          "forms": [
            {
              "type": "normform",
              "id": "qpn-x-temple.x000085",
              "ref": "qpn-x-temple.x000083",
              "icount": "1",
              "ipct": "100",
              "xis": "qpn.r00008"
            }
          ]
        }
      ],
      "senses": [
        {
          "type": "sense",
          "id": "qpn-x-temple.x000086",
          "n": "Ehulhul[1//1]TN'TN",
          "icount": "1",
          "ipct": "100",
          "xis": "qpn.r00008",
          "pos": "TN",
          "mng": "1",
          "forms": [
            {
              "type": "form",
              "id": "qpn-x-temple.x000087",
              "n": "e₂-hul₂-hul₂",
              "icount": "1",
              "ipct": "100",
              "xis": "qpn.r00008"
            }
          ],
          "norms": [
            {
              "id": "qpn-x-temple.x000088",
              "n": "Ehulhul",
              "icount": "1",
              "ipct": "100",
              "xis": "qpn.r00008"
            }
          ],
          "sigs": [
            {
              "type": "sig",
              "id": "qpn-x-temple.x000089",
              "sig": "@rinap/rinap4%akk:e₂-hul₂-hul₂=Ehulhul[1//1]TN'TN$Ehulhul",
              "icount": "1",
              "ipct": "100",
              "xis": "qpn.r00008"
            }
          ]
        }
      ]
    },
    {
      "headword": "Ehursaggalkurkurra[1]TN",
      "id": "qpn-x-temple.x000011",
      "icount": "4",
      "ipct": "100",
      "xis": "qpn.r00009",
      "cf": "Ehursaggalkurkurra",
      "gw": "1",
      "pos": "TN",
      "forms": [
        {
          "type": "form",
          "id": "qpn-x-temple.x000090",
          "n": "e₂-hur-sag-gal-kur-kur-ra",
          "icount": "4",
          "ipct": "100",
          "xis": "qpn.r00009"
        }
      ],
      "norms": [
        {
          "id": "qpn-x-temple.x000091",
          "icount": "4",
          "ipct": "100",
          "xis": "qpn.r00009",
          "n": "Ehursaggalkurkurra",
          "forms": [
            {
              "type": "normform",
              "id": "qpn-x-temple.x000092",
              "ref": "qpn-x-temple.x000090",
              "icount": "4",
              "ipct": "100",
              "xis": "qpn.r00009"
            }
          ]
        }
      ],
      "senses": [
        {
          "type": "sense",
          "id": "qpn-x-temple.x000093",
          "n": "Ehursaggalkurkurra[1//1]TN'TN",
          "icount": "4",
          "ipct": "100",
          "xis": "qpn.r00009",
          "pos": "TN",
          "mng": "1",
          "forms": [
            {
              "type": "form",
              "id": "qpn-x-temple.x000094",
              "n": "e₂-hur-sag-gal-kur-kur-ra",
              "icount": "4",
              "ipct": "100",
              "xis": "qpn.r00009"
            }
          ],
          "norms": [
            {
              "id": "qpn-x-temple.x000095",
              "n": "Ehursaggalkurkurra",
              "icount": "4",
              "ipct": "100",
              "xis": "qpn.r00009"
            }
          ],
          "sigs": [
            {
              "type": "sig",
              "id": "qpn-x-temple.x000096",
              "sig": "@rinap/rinap4%akk:e₂-hur-sag-gal-kur-kur-ra=Ehursaggalkurkurra[1//1]TN'TN$Ehursaggalkurkurra",
              "icount": "4",
              "ipct": "100",
              "xis": "qpn.r00009"
            }
          ]
        }
      ]
    },
    {
      "headword": "Ehursaggula[1]TN",
      "id": "qpn-x-temple.x000012",
      "icount": "1",
      "ipct": "100",
      "xis": "qpn.r0000a",
      "cf": "Ehursaggula",
      "gw": "1",
      "pos": "TN",
      "forms": [
        {
          "type": "form",
          "id": "qpn-x-temple.x000097",
          "n": "e₂-hur-sag-gu-la",
          "icount": "1",
          "ipct": "100",
          "xis": "qpn.r0000a"
        }
      ],
      "norms": [
        {
          "id": "qpn-x-temple.x000098",
          "icount": "1",
          "ipct": "100",
          "xis": "qpn.r0000a",
          "n": "Ehursaggula",
          "forms": [
            {
              "type": "normform",
              "id": "qpn-x-temple.x000099",
              "ref": "qpn-x-temple.x000097",
              "icount": "1",
              "ipct": "100",
              "xis": "qpn.r0000a"
            }
          ]
        }
      ],
      "senses": [
        {
          "type": "sense",
          "id": "qpn-x-temple.x000100",
          "n": "Ehursaggula[1//1]TN'TN",
          "icount": "1",
          "ipct": "100",
          "xis": "qpn.r0000a",
          "pos": "TN",
          "mng": "1",
          "forms": [
            {
              "type": "form",
              "id": "qpn-x-temple.x000101",
              "n": "e₂-hur-sag-gu-la",
              "icount": "1",
              "ipct": "100",
              "xis": "qpn.r0000a"
            }
          ],
          "norms": [
            {
              "id": "qpn-x-temple.x000102",
              "n": "Ehursaggula",
              "icount": "1",
              "ipct": "100",
              "xis": "qpn.r0000a"
            }
          ],
          "sigs": [
            {
              "type": "sig",
              "id": "qpn-x-temple.x000103",
              "sig": "@rinap/rinap4%akk:e₂-hur-sag-gu-la=Ehursaggula[1//1]TN'TN$Ehursaggula",
              "icount": "1",
              "ipct": "100",
              "xis": "qpn.r0000a"
            }
          ]
        }
      ]
    },
    {
      "headword": "Ekarzagina[1]TN",
      "id": "qpn-x-temple.x000013",
      "icount": "2",
      "ipct": "100",
      "xis": "qpn.r0000b",
      "cf": "Ekarzagina",
      "gw": "1",
      "pos": "TN",
      "forms": [
        {
          "type": "form",
          "id": "qpn-x-temple.x000104",
          "n": "e₂-kar-za-gin₃-na",
          "icount": "2",
          "ipct": "100",
          "xis": "qpn.r0000b"
        }
      ],
      "norms": [
        {
          "id": "qpn-x-temple.x000105",
          "icount": "2",
          "ipct": "100",
          "xis": "qpn.r0000b",
          "n": "Ekarzagina",
          "forms": [
            {
              "type": "normform",
              "id": "qpn-x-temple.x000106",
              "ref": "qpn-x-temple.x000104",
              "icount": "2",
              "ipct": "100",
              "xis": "qpn.r0000b"
            }
          ]
        }
      ],
      "senses": [
        {
          "type": "sense",
          "id": "qpn-x-temple.x000107",
          "n": "Ekarzagina[1//1]TN'TN",
          "icount": "2",
          "ipct": "100",
          "xis": "qpn.r0000b",
          "pos": "TN",
          "mng": "1",
          "forms": [
            {
              "type": "form",
              "id": "qpn-x-temple.x000108",
              "n": "e₂-kar-za-gin₃-na",
              "icount": "2",
              "ipct": "100",
              "xis": "qpn.r0000b"
            }
          ],
          "norms": [
            {
              "id": "qpn-x-temple.x000109",
              "n": "Ekarzagina",
              "icount": "2",
              "ipct": "100",
              "xis": "qpn.r0000b"
            }
          ],
          "sigs": [
            {
              "type": "sig",
              "id": "qpn-x-temple.x000110",
              "sig": "@rinap/rinap4%akk:e₂-kar-za-gin₃-na=Ekarzagina[1//1]TN'TN$Ekarzagina",
              "icount": "2",
              "ipct": "100",
              "xis": "qpn.r0000b"
            }
          ]
        }
      ]
    },
    {
      "headword": "Ekur[1]TN",
      "id": "qpn-x-temple.x000000",
      "icount": "5",
      "ipct": "100",
      "xis": "qpn.r0000c",
      "cf": "Ekur",
      "gw": "1",
      "pos": "TN",
      "forms": [
        {
          "type": "form",
          "id": "qpn-x-temple.x000111",
          "n": "E₂.KUR",
          "icount": "1",
          "ipct": "20",
          "xis": "qpn.r0000d"
        },
        {
          "type": "form",
          "id": "qpn-x-temple.x000112",
          "n": "e₂-kur",
          "icount": "4",
          "ipct": "80",
          "xis": "qpn.r0000e"
        }
      ],
      "norms": [
        {
          "id": "qpn-x-temple.x000113",
          "icount": "5",
          "ipct": "100",
          "xis": "qpn.r0000c",
          "n": "Ekur",
          "forms": [
            {
              "type": "normform",
              "id": "qpn-x-temple.x000114",
              "ref": "qpn-x-temple.x000111",
              "icount": "1",
              "ipct": "20",
              "xis": "qpn.r0000d"
            },
            {
              "type": "normform",
              "id": "qpn-x-temple.x000115",
              "ref": "qpn-x-temple.x000112",
              "icount": "4",
              "ipct": "80",
              "xis": "qpn.r0000e"
            }
          ]
        }
      ],
      "senses": [
        {
          "type": "sense",
          "id": "qpn-x-temple.x000116",
          "n": "Ekur[1//1]TN'TN",
          "icount": "5",
          "ipct": "100",
          "xis": "qpn.r0000c",
          "pos": "TN",
          "mng": "1",
          "forms": [
            {
              "type": "form",
              "id": "qpn-x-temple.x000117",
              "n": "E₂.KUR",
              "icount": "1",
              "ipct": "20",
              "xis": "qpn.r0000d"
            },
            {
              "type": "form",
              "id": "qpn-x-temple.x000118",
              "n": "e₂-kur",
              "icount": "4",
              "ipct": "80",
              "xis": "qpn.r0000e"
            }
          ],
          "norms": [
            {
              "id": "qpn-x-temple.x000119",
              "n": "Ekur",
              "icount": "5",
              "ipct": "100",
              "xis": "qpn.r0000c"
            }
          ],
          "sigs": [
            {
              "type": "sig",
              "id": "qpn-x-temple.x000120",
              "sig": "@rinap/rinap4%akk:E₂.KUR=Ekur[1//1]TN'TN$Ekur",
              "icount": "1",
              "ipct": "20",
              "xis": "qpn.r0000d"
            },
            {
              "type": "sig",
              "id": "qpn-x-temple.x000121",
              "sig": "@rinap/rinap4%akk:e₂-kur=Ekur[1//1]TN'TN$Ekur",
              "icount": "4",
              "ipct": "80",
              "xis": "qpn.r0000e"
            }
          ]
        }
      ]
    },
    {
      "headword": "Emašmaš[1]TN",
      "id": "qpn-x-temple.x000014",
      "icount": "3",
      "ipct": "100",
      "xis": "qpn.r0000f",
      "cf": "Emašmaš",
      "gw": "1",
      "pos": "TN",
      "forms": [
        {
          "type": "form",
          "id": "qpn-x-temple.x000122",
          "n": "e₂-maš-maš",
          "icount": "3",
          "ipct": "100",
          "xis": "qpn.r0000f"
        }
      ],
      "norms": [
        {
          "id": "qpn-x-temple.x000123",
          "icount": "3",
          "ipct": "100",
          "xis": "qpn.r0000f",
          "n": "Emašmaš",
          "forms": [
            {
              "type": "normform",
              "id": "qpn-x-temple.x000124",
              "ref": "qpn-x-temple.x000122",
              "icount": "3",
              "ipct": "100",
              "xis": "qpn.r0000f"
            }
          ]
        }
      ],
      "senses": [
        {
          "type": "sense",
          "id": "qpn-x-temple.x000125",
          "n": "Emašmaš[1//1]TN'TN",
          "icount": "3",
          "ipct": "100",
          "xis": "qpn.r0000f",
          "pos": "TN",
          "mng": "1",
          "forms": [
            {
              "type": "form",
              "id": "qpn-x-temple.x000126",
              "n": "e₂-maš-maš",
              "icount": "3",
              "ipct": "100",
              "xis": "qpn.r0000f"
            }
          ],
          "norms": [
            {
              "id": "qpn-x-temple.x000127",
              "n": "Emašmaš",
              "icount": "3",
              "ipct": "100",
              "xis": "qpn.r0000f"
            }
          ],
          "sigs": [
            {
              "type": "sig",
              "id": "qpn-x-temple.x000128",
              "sig": "@rinap/rinap4%akk:e₂-maš-maš=Emašmaš[1//1]TN'TN$Emašmaš",
              "icount": "3",
              "ipct": "100",
              "xis": "qpn.r0000f"
            }
          ]
        }
      ]
    },
    {
      "headword": "Enamtaggadua[1]TN",
      "id": "qpn-x-temple.x000015",
      "icount": "1",
      "ipct": "100",
      "xis": "qpn.r00010",
      "cf": "Enamtaggadua",
      "gw": "1",
      "pos": "TN",
      "forms": [
        {
          "type": "form",
          "id": "qpn-x-temple.x000129",
          "n": "e₂-nam-tag-ga-du₈-a",
          "icount": "1",
          "ipct": "100",
          "xis": "qpn.r00010"
        }
      ],
      "norms": [
        {
          "id": "qpn-x-temple.x000130",
          "icount": "1",
          "ipct": "100",
          "xis": "qpn.r00010",
          "n": "Enamtaggadua",
          "forms": [
            {
              "type": "normform",
              "id": "qpn-x-temple.x000131",
              "ref": "qpn-x-temple.x000129",
              "icount": "1",
              "ipct": "100",
              "xis": "qpn.r00010"
            }
          ]
        }
      ],
      "senses": [
        {
          "type": "sense",
          "id": "qpn-x-temple.x000132",
          "n": "Enamtaggadua[1//1]TN'TN",
          "icount": "1",
          "ipct": "100",
          "xis": "qpn.r00010",
          "pos": "TN",
          "mng": "1",
          "forms": [
            {
              "type": "form",
              "id": "qpn-x-temple.x000133",
              "n": "e₂-nam-tag-ga-du₈-a",
              "icount": "1",
              "ipct": "100",
              "xis": "qpn.r00010"
            }
          ],
          "norms": [
            {
              "id": "qpn-x-temple.x000134",
              "n": "Enamtaggadua",
              "icount": "1",
              "ipct": "100",
              "xis": "qpn.r00010"
            }
          ],
          "sigs": [
            {
              "type": "sig",
              "id": "qpn-x-temple.x000135",
              "sig": "@rinap/rinap4%akk:e₂-nam-tag-ga-du₈-a=Enamtaggadua[1//1]TN'TN$Enamtaggadua",
              "icount": "1",
              "ipct": "100",
              "xis": "qpn.r00010"
            }
          ]
        }
      ]
    },
    {
      "headword": "Eniggidrukalamasuma[1]TN",
      "id": "qpn-x-temple.x000016",
      "icount": "2",
      "ipct": "100",
      "xis": "qpn.r00011",
      "cf": "Eniggidrukalamasuma",
      "gw": "1",
      "pos": "TN",
      "forms": [
        {
          "type": "form",
          "id": "qpn-x-temple.x000136",
          "n": "e₂-nig₂-gidru-kalam-ma-sum-ma",
          "icount": "2",
          "ipct": "100",
          "xis": "qpn.r00011"
        }
      ],
      "norms": [
        {
          "id": "qpn-x-temple.x000137",
          "icount": "2",
          "ipct": "100",
          "xis": "qpn.r00011",
          "n": "Eniggidrukalamasuma",
          "forms": [
            {
              "type": "normform",
              "id": "qpn-x-temple.x000138",
              "ref": "qpn-x-temple.x000136",
              "icount": "2",
              "ipct": "100",
              "xis": "qpn.r00011"
            }
          ]
        }
      ],
      "senses": [
        {
          "type": "sense",
          "id": "qpn-x-temple.x000139",
          "n": "Eniggidrukalamasuma[1//1]TN'TN",
          "icount": "2",
          "ipct": "100",
          "xis": "qpn.r00011",
          "pos": "TN",
          "mng": "1",
          "forms": [
            {
              "type": "form",
              "id": "qpn-x-temple.x000140",
              "n": "e₂-nig₂-gidru-kalam-ma-sum-ma",
              "icount": "2",
              "ipct": "100",
              "xis": "qpn.r00011"
            }
          ],
          "norms": [
            {
              "id": "qpn-x-temple.x000141",
              "n": "Eniggidrukalamasuma",
              "icount": "2",
              "ipct": "100",
              "xis": "qpn.r00011"
            }
          ],
          "sigs": [
            {
              "type": "sig",
              "id": "qpn-x-temple.x000142",
              "sig": "@rinap/rinap4%akk:e₂-nig₂-gidru-kalam-ma-sum-ma=Eniggidrukalamasuma[1//1]TN'TN$Eniggidrukalamasuma",
              "icount": "2",
              "ipct": "100",
              "xis": "qpn.r00011"
            }
          ]
        }
      ]
    },
    {
      "headword": "Enirgalana[1]TN",
      "id": "qpn-x-temple.x000017",
      "icount": "3",
      "ipct": "100",
      "xis": "qpn.r00012",
      "cf": "Enirgalana",
      "gw": "1",
      "pos": "TN",
      "forms": [
        {
          "type": "form",
          "id": "qpn-x-temple.x000143",
          "n": "e₂-nir-gal₂-an-na",
          "icount": "3",
          "ipct": "100",
          "xis": "qpn.r00012"
        }
      ],
      "norms": [
        {
          "id": "qpn-x-temple.x000144",
          "icount": "3",
          "ipct": "100",
          "xis": "qpn.r00012",
          "n": "Enirgalana",
          "forms": [
            {
              "type": "normform",
              "id": "qpn-x-temple.x000145",
              "ref": "qpn-x-temple.x000143",
              "icount": "3",
              "ipct": "100",
              "xis": "qpn.r00012"
            }
          ]
        }
      ],
      "senses": [
        {
          "type": "sense",
          "id": "qpn-x-temple.x000146",
          "n": "Enirgalana[1//1]TN'TN",
          "icount": "3",
          "ipct": "100",
          "xis": "qpn.r00012",
          "pos": "TN",
          "mng": "1",
          "forms": [
            {
              "type": "form",
              "id": "qpn-x-temple.x000147",
              "n": "e₂-nir-gal₂-an-na",
              "icount": "3",
              "ipct": "100",
              "xis": "qpn.r00012"
            }
          ],
          "norms": [
            {
              "id": "qpn-x-temple.x000148",
              "n": "Enirgalana",
              "icount": "3",
              "ipct": "100",
              "xis": "qpn.r00012"
            }
          ],
          "sigs": [
            {
              "type": "sig",
              "id": "qpn-x-temple.x000149",
              "sig": "@rinap/rinap4%akk:e₂-nir-gal₂-an-na=Enirgalana[1//1]TN'TN$Enirgalana",
              "icount": "3",
              "ipct": "100",
              "xis": "qpn.r00012"
            }
          ]
        }
      ]
    },
    {
      "headword": "Esabad[1]TN",
      "id": "qpn-x-temple.x000018",
      "icount": "1",
      "ipct": "100",
      "xis": "qpn.r00013",
      "cf": "Esabad",
      "gw": "1",
      "pos": "TN",
      "forms": [
        {
          "type": "form",
          "id": "qpn-x-temple.x000150",
          "n": "e₂-sa-bad",
          "icount": "1",
          "ipct": "100",
          "xis": "qpn.r00013"
        }
      ],
      "norms": [
        {
          "id": "qpn-x-temple.x000151",
          "icount": "1",
          "ipct": "100",
          "xis": "qpn.r00013",
          "n": "Esabad",
          "forms": [
            {
              "type": "normform",
              "id": "qpn-x-temple.x000152",
              "ref": "qpn-x-temple.x000150",
              "icount": "1",
              "ipct": "100",
              "xis": "qpn.r00013"
            }
          ]
        }
      ],
      "senses": [
        {
          "type": "sense",
          "id": "qpn-x-temple.x000153",
          "n": "Esabad[1//1]TN'TN",
          "icount": "1",
          "ipct": "100",
          "xis": "qpn.r00013",
          "pos": "TN",
          "mng": "1",
          "forms": [
            {
              "type": "form",
              "id": "qpn-x-temple.x000154",
              "n": "e₂-sa-bad",
              "icount": "1",
              "ipct": "100",
              "xis": "qpn.r00013"
            }
          ],
          "norms": [
            {
              "id": "qpn-x-temple.x000155",
              "n": "Esabad",
              "icount": "1",
              "ipct": "100",
              "xis": "qpn.r00013"
            }
          ],
          "sigs": [
            {
              "type": "sig",
              "id": "qpn-x-temple.x000156",
              "sig": "@rinap/rinap4%akk:e₂-sa-bad=Esabad[1//1]TN'TN$Esabad",
              "icount": "1",
              "ipct": "100",
              "xis": "qpn.r00013"
            }
          ]
        }
      ]
    },
    {
      "headword": "Esagil[1]TN",
      "id": "qpn-x-temple.x000019",
      "icount": "81",
      "ipct": "100",
      "xis": "qpn.r00014",
      "cf": "Esagil",
      "gw": "1",
      "pos": "TN",
      "forms": [
        {
          "type": "form",
          "id": "qpn-x-temple.x000157",
          "n": "e₂-sag-gil₂",
          "icount": "44",
          "ipct": "54",
          "xis": "qpn.r00015"
        },
        {
          "type": "form",
          "id": "qpn-x-temple.x000158",
          "n": "e₂-sag-il₂",
          "icount": "37",
          "ipct": "46",
          "xis": "qpn.r00016"
        }
      ],
      "norms": [
        {
          "id": "qpn-x-temple.x000159",
          "icount": "44",
          "ipct": "54",
          "xis": "qpn.r00015",
          "n": "Esaggil",
          "forms": [
            {
              "type": "normform",
              "id": "qpn-x-temple.x000160",
              "ref": "qpn-x-temple.x000157",
              "icount": "44",
              "ipct": "54",
              "xis": "qpn.r00015"
            }
          ]
        },
        {
          "id": "qpn-x-temple.x000161",
          "icount": "37",
          "ipct": "46",
          "xis": "qpn.r00016",
          "n": "Esagil",
          "forms": [
            {
              "type": "normform",
              "id": "qpn-x-temple.x000162",
              "ref": "qpn-x-temple.x000158",
              "icount": "37",
              "ipct": "46",
              "xis": "qpn.r00016"
            }
          ]
        }
      ],
      "senses": [
        {
          "type": "sense",
          "id": "qpn-x-temple.x000163",
          "n": "Esagil[1//1]TN'TN",
          "icount": "81",
          "ipct": "100",
          "xis": "qpn.r00014",
          "pos": "TN",
          "mng": "1",
          "forms": [
            {
              "type": "form",
              "id": "qpn-x-temple.x000164",
              "n": "e₂-sag-gil₂",
              "icount": "44",
              "ipct": "54",
              "xis": "qpn.r00015"
            },
            {
              "type": "form",
              "id": "qpn-x-temple.x000165",
              "n": "e₂-sag-il₂",
              "icount": "37",
              "ipct": "46",
              "xis": "qpn.r00016"
            }
          ],
          "norms": [
            {
              "id": "qpn-x-temple.x000166",
              "n": "Esaggil",
              "icount": "44",
              "ipct": "54",
              "xis": "qpn.r00015"
            },
            {
              "id": "qpn-x-temple.x000167",
              "n": "Esagil",
              "icount": "37",
              "ipct": "46",
              "xis": "qpn.r00016"
            }
          ],
          "sigs": [
            {
              "type": "sig",
              "id": "qpn-x-temple.x000168",
              "sig": "@rinap/rinap4%akk:e₂-sag-gil₂=Esagil[1//1]TN'TN$Esaggil",
              "icount": "44",
              "ipct": "54",
              "xis": "qpn.r00015"
            },
            {
              "type": "sig",
              "id": "qpn-x-temple.x000169",
              "sig": "@rinap/rinap4%akk:e₂-sag-il₂=Esagil[1//1]TN'TN$Esagil",
              "icount": "37",
              "ipct": "46",
              "xis": "qpn.r00016"
            }
          ]
        }
      ]
    },
    {
      "headword": "Etemenanki[1]TN",
      "id": "qpn-x-temple.x000020",
      "icount": "9",
      "ipct": "100",
      "xis": "qpn.r00017",
      "cf": "Etemenanki",
      "gw": "1",
      "pos": "TN",
      "forms": [
        {
          "type": "form",
          "id": "qpn-x-temple.x000170",
          "n": "e₂-te-me-en-an-ki",
          "icount": "4",
          "ipct": "44",
          "xis": "qpn.r00018"
        },
        {
          "type": "form",
          "id": "qpn-x-temple.x000171",
          "n": "e₂-temen-an-ki",
          "icount": "4",
          "ipct": "44",
          "xis": "qpn.r00019"
        },
        {
          "type": "form",
          "id": "qpn-x-temple.x000172",
          "n": "e₂-te-me-en-an-ki",
          "icount": "1",
          "ipct": "11",
          "xis": "qpn.r0001a"
        }
      ],
      "norms": [
        {
          "id": "qpn-x-temple.x000173",
          "icount": "9",
          "ipct": "100",
          "xis": "qpn.r00017",
          "n": "Etemenanki",
          "forms": [
            {
              "type": "normform",
              "id": "qpn-x-temple.x000174",
              "ref": "qpn-x-temple.x000170",
              "icount": "4",
              "ipct": "44",
              "xis": "qpn.r00018"
            },
            {
              "type": "normform",
              "id": "qpn-x-temple.x000175",
              "ref": "qpn-x-temple.x000171",
              "icount": "4",
              "ipct": "44",
              "xis": "qpn.r00019"
            },
            {
              "type": "normform",
              "id": "qpn-x-temple.x000176",
              "ref": "qpn-x-temple.x000172",
              "icount": "1",
              "ipct": "11",
              "xis": "qpn.r0001a"
            }
          ]
        }
      ],
      "bases": [
        {
          "type": "base",
          "id": "qpn-x-temple.x000177",
          "n": "e₂-te-me-en-an-ki",
          "icount": "1",
          "ipct": "11",
          "xis": "qpn.r0001a"
        }
      ],
      "morphs": [
        {
          "type": "morph",
          "id": "qpn-x-temple.x000178",
          "n": "~",
          "icount": "1",
          "ipct": "11",
          "xis": "qpn.r0001a"
        }
      ],
      "senses": [
        {
          "type": "sense",
          "id": "qpn-x-temple.x000179",
          "n": "Etemenanki[1//1]TN'TN",
          "icount": "9",
          "ipct": "100",
          "xis": "qpn.r00017",
          "pos": "TN",
          "mng": "1",
          "forms": [
            {
              "type": "form",
              "id": "qpn-x-temple.x000180",
              "n": "e₂-te-me-en-an-ki",
              "icount": "4",
              "ipct": "44",
              "xis": "qpn.r00018"
            },
            {
              "type": "form",
              "id": "qpn-x-temple.x000181",
              "n": "e₂-temen-an-ki",
              "icount": "4",
              "ipct": "44",
              "xis": "qpn.r00019"
            },
            {
              "type": "form",
              "id": "qpn-x-temple.x000182",
              "n": "e₂-te-me-en-an-ki",
              "icount": "1",
              "ipct": "11",
              "xis": "qpn.r0001a"
            }
          ],
          "norms": [
            {
              "id": "qpn-x-temple.x000183",
              "n": "Etemenanki",
              "icount": "9",
              "ipct": "100",
              "xis": "qpn.r00017"
            }
          ],
          "bases": [
            {
              "type": "base",
              "id": "qpn-x-temple.x000184",
              "n": "e₂-te-me-en-an-ki",
              "icount": "1",
              "ipct": "11",
              "xis": "qpn.r0001a"
            }
          ],
          "morphs": [
            {
              "type": "morph",
              "id": "qpn-x-temple.x000185",
              "n": "~",
              "icount": "1",
              "ipct": "11",
              "xis": "qpn.r0001a"
            }
          ],
          "sigs": [
            {
              "type": "sig",
              "id": "qpn-x-temple.x000186",
              "sig": "@rinap/rinap4%akk:e₂-te-me-en-an-ki=Etemenanki[1//1]TN'TN$Etemenanki",
              "icount": "4",
              "ipct": "44",
              "xis": "qpn.r00018"
            },
            {
              "type": "sig",
              "id": "qpn-x-temple.x000187",
              "sig": "@rinap/rinap4%akk:e₂-temen-an-ki=Etemenanki[1//1]TN'TN$Etemenanki",
              "icount": "4",
              "ipct": "44",
              "xis": "qpn.r00019"
            },
            {
              "type": "sig",
              "id": "qpn-x-temple.x000188",
              "sig": "@rinap/rinap4%sux:e₂-te-me-en-an-ki=Etemenanki[1//1]TN'TN$Etemenanki/e₂-te-me-en-an-ki#~",
              "icount": "1",
              "ipct": "11",
              "xis": "qpn.r0001a"
            }
          ]
        }
      ]
    },
    {
      "headword": "Eumuša[1]TN",
      "id": "qpn-x-temple.x000021",
      "icount": "2",
      "ipct": "100",
      "xis": "qpn.r0001b",
      "cf": "Eumuša",
      "gw": "1",
      "pos": "TN",
      "forms": [
        {
          "type": "form",
          "id": "qpn-x-temple.x000189",
          "n": "e₂-umuš-a",
          "icount": "2",
          "ipct": "100",
          "xis": "qpn.r0001b"
        }
      ],
      "norms": [
        {
          "id": "qpn-x-temple.x000190",
          "icount": "2",
          "ipct": "100",
          "xis": "qpn.r0001b",
          "n": "Eumuša",
          "forms": [
            {
              "type": "normform",
              "id": "qpn-x-temple.x000191",
              "ref": "qpn-x-temple.x000189",
              "icount": "2",
              "ipct": "100",
              "xis": "qpn.r0001b"
            }
          ]
        }
      ],
      "senses": [
        {
          "type": "sense",
          "id": "qpn-x-temple.x000192",
          "n": "Eumuša[1//1]TN'TN",
          "icount": "2",
          "ipct": "100",
          "xis": "qpn.r0001b",
          "pos": "TN",
          "mng": "1",
          "forms": [
            {
              "type": "form",
              "id": "qpn-x-temple.x000193",
              "n": "e₂-umuš-a",
              "icount": "2",
              "ipct": "100",
              "xis": "qpn.r0001b"
            }
          ],
          "norms": [
            {
              "id": "qpn-x-temple.x000194",
              "n": "Eumuša",
              "icount": "2",
              "ipct": "100",
              "xis": "qpn.r0001b"
            }
          ],
          "sigs": [
            {
              "type": "sig",
              "id": "qpn-x-temple.x000195",
              "sig": "@rinap/rinap4%akk:e₂-umuš-a=Eumuša[1//1]TN'TN$Eumuša",
              "icount": "2",
              "ipct": "100",
              "xis": "qpn.r0001b"
            }
          ]
        }
      ]
    },
    {
      "headword": "Ezida[1]TN",
      "id": "qpn-x-temple.x000022",
      "icount": "3",
      "ipct": "100",
      "xis": "qpn.r0001c",
      "cf": "Ezida",
      "gw": "1",
      "pos": "TN",
      "forms": [
        {
          "type": "form",
          "id": "qpn-x-temple.x000196",
          "n": "e₂-zi-da",
          "icount": "3",
          "ipct": "100",
          "xis": "qpn.r0001c"
        }
      ],
      "norms": [
        {
          "id": "qpn-x-temple.x000197",
          "icount": "3",
          "ipct": "100",
          "xis": "qpn.r0001c",
          "n": "Ezida",
          "forms": [
            {
              "type": "normform",
              "id": "qpn-x-temple.x000198",
              "ref": "qpn-x-temple.x000196",
              "icount": "3",
              "ipct": "100",
              "xis": "qpn.r0001c"
            }
          ]
        }
      ],
      "senses": [
        {
          "type": "sense",
          "id": "qpn-x-temple.x000199",
          "n": "Ezida[1//1]TN'TN",
          "icount": "3",
          "ipct": "100",
          "xis": "qpn.r0001c",
          "pos": "TN",
          "mng": "1",
          "forms": [
            {
              "type": "form",
              "id": "qpn-x-temple.x000200",
              "n": "e₂-zi-da",
              "icount": "3",
              "ipct": "100",
              "xis": "qpn.r0001c"
            }
          ],
          "norms": [
            {
              "id": "qpn-x-temple.x000201",
              "n": "Ezida",
              "icount": "3",
              "ipct": "100",
              "xis": "qpn.r0001c"
            }
          ],
          "sigs": [
            {
              "type": "sig",
              "id": "qpn-x-temple.x000202",
              "sig": "@rinap/rinap4%akk:e₂-zi-da=Ezida[1//1]TN'TN$Ezida",
              "icount": "3",
              "ipct": "100",
              "xis": "qpn.r0001c"
            }
          ]
        }
      ]
    },
    {
      "headword": "Ešarra[1]TN",
      "id": "qpn-x-temple.x000023",
      "icount": "15",
      "ipct": "100",
      "xis": "qpn.r0001d",
      "cf": "Ešarra",
      "gw": "1",
      "pos": "TN",
      "forms": [
        {
          "type": "form",
          "id": "qpn-x-temple.x000203",
          "n": "e₂-šar₂-ra",
          "icount": "15",
          "ipct": "100",
          "xis": "qpn.r0001d"
        }
      ],
      "norms": [
        {
          "id": "qpn-x-temple.x000204",
          "icount": "15",
          "ipct": "100",
          "xis": "qpn.r0001d",
          "n": "Ešarra",
          "forms": [
            {
              "type": "normform",
              "id": "qpn-x-temple.x000205",
              "ref": "qpn-x-temple.x000203",
              "icount": "15",
              "ipct": "100",
              "xis": "qpn.r0001d"
            }
          ]
        }
      ],
      "senses": [
        {
          "type": "sense",
          "id": "qpn-x-temple.x000206",
          "n": "Ešarra[1//1]TN'TN",
          "icount": "15",
          "ipct": "100",
          "xis": "qpn.r0001d",
          "pos": "TN",
          "mng": "1",
          "forms": [
            {
              "type": "form",
              "id": "qpn-x-temple.x000207",
              "n": "e₂-šar₂-ra",
              "icount": "15",
              "ipct": "100",
              "xis": "qpn.r0001d"
            }
          ],
          "norms": [
            {
              "id": "qpn-x-temple.x000208",
              "n": "Ešarra",
              "icount": "15",
              "ipct": "100",
              "xis": "qpn.r0001d"
            }
          ],
          "sigs": [
            {
              "type": "sig",
              "id": "qpn-x-temple.x000209",
              "sig": "@rinap/rinap4%akk:e₂-šar₂-ra=Ešarra[1//1]TN'TN$Ešarra",
              "icount": "15",
              "ipct": "100",
              "xis": "qpn.r0001d"
            }
          ]
        }
      ]
    },
    {
      "headword": "Ešeriga[1]TN",
      "id": "qpn-x-temple.x000024",
      "icount": "1",
      "ipct": "100",
      "xis": "qpn.r0001e",
      "cf": "Ešeriga",
      "gw": "1",
      "pos": "TN",
      "forms": [
        {
          "type": "form",
          "id": "qpn-x-temple.x000210",
          "n": "e₂-še-ri-ga",
          "icount": "1",
          "ipct": "100",
          "xis": "qpn.r0001e"
        }
      ],
      "norms": [
        {
          "id": "qpn-x-temple.x000211",
          "icount": "1",
          "ipct": "100",
          "xis": "qpn.r0001e",
          "n": "Ešeriga",
          "forms": [
            {
              "type": "normform",
              "id": "qpn-x-temple.x000212",
              "ref": "qpn-x-temple.x000210",
              "icount": "1",
              "ipct": "100",
              "xis": "qpn.r0001e"
            }
          ]
        }
      ],
      "senses": [
        {
          "type": "sense",
          "id": "qpn-x-temple.x000213",
          "n": "Ešeriga[1//1]TN'TN",
          "icount": "1",
          "ipct": "100",
          "xis": "qpn.r0001e",
          "pos": "TN",
          "mng": "1",
          "forms": [
            {
              "type": "form",
              "id": "qpn-x-temple.x000214",
              "n": "e₂-še-ri-ga",
              "icount": "1",
              "ipct": "100",
              "xis": "qpn.r0001e"
            }
          ],
          "norms": [
            {
              "id": "qpn-x-temple.x000215",
              "n": "Ešeriga",
              "icount": "1",
              "ipct": "100",
              "xis": "qpn.r0001e"
            }
          ],
          "sigs": [
            {
              "type": "sig",
              "id": "qpn-x-temple.x000216",
              "sig": "@rinap/rinap4%akk:e₂-še-ri-ga=Ešeriga[1//1]TN'TN$Ešeriga",
              "icount": "1",
              "ipct": "100",
              "xis": "qpn.r0001e"
            }
          ]
        }
      ]
    },
    {
      "headword": "Ešgalšiddudua[1]TN",
      "id": "qpn-x-temple.x000002",
      "icount": "2",
      "ipct": "100",
      "xis": "qpn.r0001f",
      "cf": "Ešgalšiddudua",
      "gw": "1",
      "pos": "TN",
      "forms": [
        {
          "type": "form",
          "id": "qpn-x-temple.x000217",
          "n": "eš₃-gal-šid-du₃-du₃-a",
          "icount": "2",
          "ipct": "100",
          "xis": "qpn.r0001f"
        }
      ],
      "norms": [
        {
          "id": "qpn-x-temple.x000218",
          "icount": "2",
          "ipct": "100",
          "xis": "qpn.r0001f",
          "n": "Ešgalšiddudua",
          "forms": [
            {
              "type": "normform",
              "id": "qpn-x-temple.x000219",
              "ref": "qpn-x-temple.x000217",
              "icount": "2",
              "ipct": "100",
              "xis": "qpn.r0001f"
            }
          ]
        }
      ],
      "senses": [
        {
          "type": "sense",
          "id": "qpn-x-temple.x000220",
          "n": "Ešgalšiddudua[1//1]TN'TN",
          "icount": "2",
          "ipct": "100",
          "xis": "qpn.r0001f",
          "pos": "TN",
          "mng": "1",
          "forms": [
            {
              "type": "form",
              "id": "qpn-x-temple.x000221",
              "n": "eš₃-gal-šid-du₃-du₃-a",
              "icount": "2",
              "ipct": "100",
              "xis": "qpn.r0001f"
            }
          ],
          "norms": [
            {
              "id": "qpn-x-temple.x000222",
              "n": "Ešgalšiddudua",
              "icount": "2",
              "ipct": "100",
              "xis": "qpn.r0001f"
            }
          ],
          "sigs": [
            {
              "type": "sig",
              "id": "qpn-x-temple.x000223",
              "sig": "@rinap/rinap4%akk:eš₃-gal-šid-du₃-du₃-a=Ešgalšiddudua[1//1]TN'TN$Ešgalšiddudua",
              "icount": "2",
              "ipct": "100",
              "xis": "qpn.r0001f"
            }
          ]
        }
      ]
    },
    {
      "headword": "Kahilisu[1]TN",
      "id": "qpn-x-temple.x000025",
      "icount": "1",
      "ipct": "100",
      "xis": "qpn.r00020",
      "cf": "Kahilisu",
      "gw": "1",
      "pos": "TN",
      "forms": [
        {
          "type": "form",
          "id": "qpn-x-temple.x000224",
          "n": "ka₂-hi-li-su₃",
          "icount": "1",
          "ipct": "100",
          "xis": "qpn.r00020"
        }
      ],
      "norms": [
        {
          "id": "qpn-x-temple.x000225",
          "icount": "1",
          "ipct": "100",
          "xis": "qpn.r00020",
          "n": "Kahilisu",
          "forms": [
            {
              "type": "normform",
              "id": "qpn-x-temple.x000226",
              "ref": "qpn-x-temple.x000224",
              "icount": "1",
              "ipct": "100",
              "xis": "qpn.r00020"
            }
          ]
        }
      ],
      "senses": [
        {
          "type": "sense",
          "id": "qpn-x-temple.x000227",
          "n": "Kahilisu[1//1]TN'TN",
          "icount": "1",
          "ipct": "100",
          "xis": "qpn.r00020",
          "pos": "TN",
          "mng": "1",
          "forms": [
            {
              "type": "form",
              "id": "qpn-x-temple.x000228",
              "n": "ka₂-hi-li-su₃",
              "icount": "1",
              "ipct": "100",
              "xis": "qpn.r00020"
            }
          ],
          "norms": [
            {
              "id": "qpn-x-temple.x000229",
              "n": "Kahilisu",
              "icount": "1",
              "ipct": "100",
              "xis": "qpn.r00020"
            }
          ],
          "sigs": [
            {
              "type": "sig",
              "id": "qpn-x-temple.x000230",
              "sig": "@rinap/rinap4%akk:ka₂-hi-li-su₃=Kahilisu[1//1]TN'TN$Kahilisu",
              "icount": "1",
              "ipct": "100",
              "xis": "qpn.r00020"
            }
          ]
        }
      ]
    },
    {
      "headword": "Pukudadaga[1]TN",
      "id": "qpn-x-temple.x000026",
      "icount": "1",
      "ipct": "100",
      "xis": "qpn.r00021",
      "cf": "Pukudadaga",
      "gw": "1",
      "pos": "TN",
      "forms": [
        {
          "type": "form",
          "id": "qpn-x-temple.x000231",
          "n": "pu₂-ku₃-dadag-ga",
          "icount": "1",
          "ipct": "100",
          "xis": "qpn.r00021"
        }
      ],
      "norms": [
        {
          "id": "qpn-x-temple.x000232",
          "icount": "1",
          "ipct": "100",
          "xis": "qpn.r00021",
          "n": "Pukudadaga",
          "forms": [
            {
              "type": "normform",
              "id": "qpn-x-temple.x000233",
              "ref": "qpn-x-temple.x000231",
              "icount": "1",
              "ipct": "100",
              "xis": "qpn.r00021"
            }
          ]
        }
      ],
      "senses": [
        {
          "type": "sense",
          "id": "qpn-x-temple.x000234",
          "n": "Pukudadaga[1//1]TN'TN",
          "icount": "1",
          "ipct": "100",
          "xis": "qpn.r00021",
          "pos": "TN",
          "mng": "1",
          "forms": [
            {
              "type": "form",
              "id": "qpn-x-temple.x000235",
              "n": "pu₂-ku₃-dadag-ga",
              "icount": "1",
              "ipct": "100",
              "xis": "qpn.r00021"
            }
          ],
          "norms": [
            {
              "id": "qpn-x-temple.x000236",
              "n": "Pukudadaga",
              "icount": "1",
              "ipct": "100",
              "xis": "qpn.r00021"
            }
          ],
          "sigs": [
            {
              "type": "sig",
              "id": "qpn-x-temple.x000237",
              "sig": "@rinap/rinap4%akk:pu₂-ku₃-dadag-ga=Pukudadaga[1//1]TN'TN$Pukudadaga",
              "icount": "1",
              "ipct": "100",
              "xis": "qpn.r00021"
            }
          ]
        }
      ]
    }
  ],
  "instances": {
    "qpn.r00004": [
      "rinap/rinap4:Q003373.19.1"
    ],
    "qpn.r00003": [
      "rinap/rinap4:Q003357.10.8",
      "rinap/rinap4:Q003358.19.8",
      "rinap/rinap4:Q003359.19.8",
      "rinap/rinap4:Q003362.20.8"
    ],
    "qpn.r00001": [
      "rinap/rinap4:Q003357.15.2",
      "rinap/rinap4:Q003357.23.2",
      "rinap/rinap4:Q003357.3.4"
    ],
    "qpn.r00000": [
      "rinap/rinap4:Q003362.16.9",
      "rinap/rinap4:Q003362.30.2",
      "rinap/rinap4:Q003362.7.3",
      "rinap/rinap4:Q003363.11.8",
      "rinap/rinap4:Q003363.5.5",
      "rinap/rinap4:Q003363.9.2",
      "rinap/rinap4:Q003364.11.8",
      "rinap/rinap4:Q003364.5.5",
      "rinap/rinap4:Q003364.9.2",
      "rinap/rinap4:Q003365.5.2",
      "rinap/rinap4:Q003366.11.3",
      "rinap/rinap4:Q003367.3.3",
      "rinap/rinap4:Q003368.2.2",
      "rinap/rinap4:Q003368.9.1",
      "rinap/rinap4:Q003382.22.6"
    ],
    "qpn.r00002": [
      "rinap/rinap4:Q003282.15.3"
    ],
    "qpn.r00005": [
      "rinap/rinap4:Q003283.59.2",
      "rinap/rinap4:Q003306.8.1",
      "rinap/rinap4:Q003307.8.1",
      "rinap/rinap4:Q003308.8.1",
      "rinap/rinap4:Q003322.4.12"
    ],
    "qpn.r00007": [
      "rinap/rinap4:Q003364.11.1",
      "rinap/rinap4:Q003364.5.2",
      "rinap/rinap4:Q003365.11.1"
    ],
    "qpn.r00006": [
      "rinap/rinap4:Q003277.93.2",
      "rinap/rinap4:Q003280.27.5"
    ],
    "qpn.r00009": [
      "rinap/rinap4:Q003274.48.1",
      "rinap/rinap4:Q003277.98.18",
      "rinap/rinap4:Q003289.40.2",
      "rinap/rinap4:Q003289.45.4"
    ],
    "qpn.r00008": [
      "rinap/rinap4:Q003285.5.2"
    ],
    "qpn.r00011": [
      "rinap/rinap4:Q003342.20.3",
      "rinap/rinap4:Q003342.24.2"
    ],
    "qpn.r00012": [
      "rinap/rinap4:Q003362.6.6",
      "rinap/rinap4:Q003363.11.1",
      "rinap/rinap4:Q003363.5.2"
    ],
    "qpn.r00013": [
      "rinap/rinap4:Q003280.26.3"
    ],
    "qpn.r00018": [
      "rinap/rinap4:Q003334.250.2",
      "rinap/rinap4:Q003339.9.1",
      "rinap/rinap4:Q003345.45.1",
      "rinap/rinap4:Q003354.2.4"
    ],
    "qpn.r00019": [
      "rinap/rinap4:Q003350.3.2",
      "rinap/rinap4:Q003351.7.1",
      "rinap/rinap4:Q003352.8.2",
      "rinap/rinap4:Q003353.6.1"
    ],
    "qpn.r0001a": [
      "rinap/rinap4:Q003355.10.1"
    ],
    "qpn.r00016": [
      "rinap/rinap4:Q003239.3.5",
      "rinap/rinap4:Q003272.10.2",
      "rinap/rinap4:Q003274.39.2",
      "rinap/rinap4:Q003277.36.10",
      "rinap/rinap4:Q003277.58.6",
      "rinap/rinap4:Q003278.6.3",
      "rinap/rinap4:Q003280.28.5",
      "rinap/rinap4:Q003289.37.1",
      "rinap/rinap4:Q003306.5.5",
      "rinap/rinap4:Q003307.5.5",
      "rinap/rinap4:Q003308.5.5",
      "rinap/rinap4:Q003315.4.4",
      "rinap/rinap4:Q003322.3.5",
      "rinap/rinap4:Q003333.82.2",
      "rinap/rinap4:Q003334.109.2",
      "rinap/rinap4:Q003334.163.3",
      "rinap/rinap4:Q003334.173.1",
      "rinap/rinap4:Q003334.234.2",
      "rinap/rinap4:Q003334.318.1",
      "rinap/rinap4:Q003334.32.3",
      "rinap/rinap4:Q003335.64.1",
      "rinap/rinap4:Q003339.19.2",
      "rinap/rinap4:Q003341.58.2",
      "rinap/rinap4:Q003343.15.3",
      "rinap/rinap4:Q003343.72.2",
      "rinap/rinap4:Q003343.90.1",
      "rinap/rinap4:Q003357.8.7",
      "rinap/rinap4:Q003357.9.14",
      "rinap/rinap4:Q003358.15.7",
      "rinap/rinap4:Q003358.18.2",
      "rinap/rinap4:Q003359.15.7",
      "rinap/rinap4:Q003359.18.2",
      "rinap/rinap4:Q003362.16.5",
      "rinap/rinap4:Q003362.19.2",
      "rinap/rinap4:Q003363.8.5",
      "rinap/rinap4:Q003364.8.5",
      "rinap/rinap4:Q003365.4.5"
    ],
    "qpn.r00017": [
      "rinap/rinap4:Q003334.250.2",
      "rinap/rinap4:Q003339.9.1",
      "rinap/rinap4:Q003345.45.1",
      "rinap/rinap4:Q003350.3.2",
      "rinap/rinap4:Q003351.7.1",
      "rinap/rinap4:Q003352.8.2",
      "rinap/rinap4:Q003353.6.1",
      "rinap/rinap4:Q003354.2.4",
      "rinap/rinap4:Q003355.10.1"
    ],
    "qpn.r0001b": [
      "rinap/rinap4:Q003277.91.15",
      "rinap/rinap4:Q003280.25.7"
    ],
    "qpn.r0001e": [
      "rinap/rinap4:Q003283.84.3"
    ],
    "qpn.r0001c": [
      "rinap/rinap4:Q003283.53.2",
      "rinap/rinap4:Q003363.8.9",
      "rinap/rinap4:Q003364.8.9"
    ],
    "qpn.r00015": [
      "rinap/rinap4:Q003230.112.2",
      "rinap/rinap4:Q003246.7.5",
      "rinap/rinap4:Q003274.46.6",
      "rinap/rinap4:Q003277.92.9",
      "rinap/rinap4:Q003277.99.11",
      "rinap/rinap4:Q003293.3.2",
      "rinap/rinap4:Q003303.5.2",
      "rinap/rinap4:Q003304.9.2",
      "rinap/rinap4:Q003313.4.1",
      "rinap/rinap4:Q003314.4.4",
      "rinap/rinap4:Q003327.40.2",
      "rinap/rinap4:Q003328.11.2",
      "rinap/rinap4:Q003333.116.1",
      "rinap/rinap4:Q003333.139.1",
      "rinap/rinap4:Q003333.147.1",
      "rinap/rinap4:Q003333.228.2",
      "rinap/rinap4:Q003333.30.1",
      "rinap/rinap4:Q003333.93.4",
      "rinap/rinap4:Q003334.135.1",
      "rinap/rinap4:Q003334.191.2",
      "rinap/rinap4:Q003334.228.2",
      "rinap/rinap4:Q003334.94.2",
      "rinap/rinap4:Q003335.108.1",
      "rinap/rinap4:Q003335.138.1",
      "rinap/rinap4:Q003335.15.2",
      "rinap/rinap4:Q003335.163.1",
      "rinap/rinap4:Q003335.217.1",
      "rinap/rinap4:Q003335.22.1",
      "rinap/rinap4:Q003335.54.2",
      "rinap/rinap4:Q003338.50.1",
      "rinap/rinap4:Q003340.8.3",
      "rinap/rinap4:Q003342.18.1",
      "rinap/rinap4:Q003342.9.2",
      "rinap/rinap4:Q003345.30.11",
      "rinap/rinap4:Q003345.35.11",
      "rinap/rinap4:Q003345.40.2",
      "rinap/rinap4:Q003345.8.3",
      "rinap/rinap4:Q003347.4.2",
      "rinap/rinap4:Q003348.8.1",
      "rinap/rinap4:Q003349.6.1",
      "rinap/rinap4:Q003350.2.4",
      "rinap/rinap4:Q003351.6.1",
      "rinap/rinap4:Q003352.7.1",
      "rinap/rinap4:Q003376.8.4"
    ],
    "qpn.r00014": [
      "rinap/rinap4:Q003230.112.2",
      "rinap/rinap4:Q003239.3.5",
      "rinap/rinap4:Q003246.7.5",
      "rinap/rinap4:Q003272.10.2",
      "rinap/rinap4:Q003274.39.2",
      "rinap/rinap4:Q003274.46.6",
      "rinap/rinap4:Q003277.36.10",
      "rinap/rinap4:Q003277.58.6",
      "rinap/rinap4:Q003277.92.9",
      "rinap/rinap4:Q003277.99.11",
      "rinap/rinap4:Q003278.6.3",
      "rinap/rinap4:Q003280.28.5",
      "rinap/rinap4:Q003289.37.1",
      "rinap/rinap4:Q003293.3.2",
      "rinap/rinap4:Q003303.5.2",
      "rinap/rinap4:Q003304.9.2",
      "rinap/rinap4:Q003306.5.5",
      "rinap/rinap4:Q003307.5.5",
      "rinap/rinap4:Q003308.5.5",
      "rinap/rinap4:Q003313.4.1",
      "rinap/rinap4:Q003314.4.4",
      "rinap/rinap4:Q003315.4.4",
      "rinap/rinap4:Q003322.3.5",
      "rinap/rinap4:Q003327.40.2",
      "rinap/rinap4:Q003328.11.2",
      "rinap/rinap4:Q003333.116.1",
      "rinap/rinap4:Q003333.139.1",
      "rinap/rinap4:Q003333.147.1",
      "rinap/rinap4:Q003333.228.2",
      "rinap/rinap4:Q003333.30.1",
      "rinap/rinap4:Q003333.82.2",
      "rinap/rinap4:Q003333.93.4",
      "rinap/rinap4:Q003334.109.2",
      "rinap/rinap4:Q003334.135.1",
      "rinap/rinap4:Q003334.163.3",
      "rinap/rinap4:Q003334.173.1",
      "rinap/rinap4:Q003334.191.2",
      "rinap/rinap4:Q003334.228.2",
      "rinap/rinap4:Q003334.234.2",
      "rinap/rinap4:Q003334.318.1",
      "rinap/rinap4:Q003334.32.3",
      "rinap/rinap4:Q003334.94.2",
      "rinap/rinap4:Q003335.108.1",
      "rinap/rinap4:Q003335.138.1",
      "rinap/rinap4:Q003335.15.2",
      "rinap/rinap4:Q003335.163.1",
      "rinap/rinap4:Q003335.217.1",
      "rinap/rinap4:Q003335.22.1",
      "rinap/rinap4:Q003335.54.2",
      "rinap/rinap4:Q003335.64.1",
      "rinap/rinap4:Q003338.50.1",
      "rinap/rinap4:Q003339.19.2",
      "rinap/rinap4:Q003340.8.3",
      "rinap/rinap4:Q003341.58.2",
      "rinap/rinap4:Q003342.18.1",
      "rinap/rinap4:Q003342.9.2",
      "rinap/rinap4:Q003343.15.3",
      "rinap/rinap4:Q003343.72.2",
      "rinap/rinap4:Q003343.90.1",
      "rinap/rinap4:Q003345.30.11",
      "rinap/rinap4:Q003345.35.11",
      "rinap/rinap4:Q003345.40.2",
      "rinap/rinap4:Q003345.8.3",
      "rinap/rinap4:Q003347.4.2",
      "rinap/rinap4:Q003348.8.1",
      "rinap/rinap4:Q003349.6.1",
      "rinap/rinap4:Q003350.2.4",
      "rinap/rinap4:Q003351.6.1",
      "rinap/rinap4:Q003352.7.1",
      "rinap/rinap4:Q003357.8.7",
      "rinap/rinap4:Q003357.9.14",
      "rinap/rinap4:Q003358.15.7",
      "rinap/rinap4:Q003358.18.2",
      "rinap/rinap4:Q003359.15.7",
      "rinap/rinap4:Q003359.18.2",
      "rinap/rinap4:Q003362.16.5",
      "rinap/rinap4:Q003362.19.2",
      "rinap/rinap4:Q003363.8.5",
      "rinap/rinap4:Q003364.8.5",
      "rinap/rinap4:Q003365.4.5",
      "rinap/rinap4:Q003376.8.4"
    ],
    "qpn.r0001d": [
      "rinap/rinap4:Q003274.45.3",
      "rinap/rinap4:Q003277.35.8",
      "rinap/rinap4:Q003277.87.9",
      "rinap/rinap4:Q003280.17.4",
      "rinap/rinap4:Q003286.200.2",
      "rinap/rinap4:Q003286.238.2",
      "rinap/rinap4:Q003286.283.3",
      "rinap/rinap4:Q003305.15.5",
      "rinap/rinap4:Q003305.6.3",
      "rinap/rinap4:Q003305.8.2",
      "rinap/rinap4:Q003333.149.1",
      "rinap/rinap4:Q003334.175.1",
      "rinap/rinap4:Q003340.21.1",
      "rinap/rinap4:Q003387.51.3",
      "rinap/rinap4:Q003408.2.5"
    ],
    "qpn.r0001f": [
      "rinap/rinap4:Q003230.486.2",
      "rinap/rinap4:Q003231.332.1"
    ],
    "qpn.r00020": [
      "rinap/rinap4:Q003387.60.3"
    ],
    "qpn.r00021": [
      "rinap/rinap4:Q003361.4.5"
    ],
    "qpn.r0000a": [
      "rinap/rinap4:Q003286.208.1"
    ],
    "qpn.r0000b": [
      "rinap/rinap4:Q003281.12.2",
      "rinap/rinap4:Q003289.50.4"
    ],
    "qpn.r0000c": [
      "rinap/rinap4:Q003357.8.5",
      "rinap/rinap4:Q003358.15.5",
      "rinap/rinap4:Q003358.29.3",
      "rinap/rinap4:Q003359.15.5",
      "rinap/rinap4:Q003360.12.1"
    ],
    "qpn.r0000f": [
      "rinap/rinap4:Q003239.6.7",
      "rinap/rinap4:Q003283.48.5",
      "rinap/rinap4:Q003407.2.4"
    ],
    "qpn.r0000d": [
      "rinap/rinap4:Q003359.15.5"
    ],
    "qpn.r0000e": [
      "rinap/rinap4:Q003357.8.5",
      "rinap/rinap4:Q003358.15.5",
      "rinap/rinap4:Q003358.29.3",
      "rinap/rinap4:Q003360.12.1"
    ],
    "qpn.r00010": [
      "rinap/rinap4:Q003277.92.11"
    ],
    "qpn.r00004.p.s000": [
      "rinap/rinap4:Q003373.19.1"
    ],
    "qpn.r00003.p.s000": [
      "rinap/rinap4:Q003357.10.8",
      "rinap/rinap4:Q003358.19.8",
      "rinap/rinap4:Q003359.19.8",
      "rinap/rinap4:Q003362.20.8"
    ],
    "qpn.r00001.p.s000": [
      "rinap/rinap4:Q003357.3.4",
      "rinap/rinap4:Q003357.15.2",
      "rinap/rinap4:Q003357.23.2"
    ],
    "qpn.r00000.p.s000": [
      "rinap/rinap4:Q003362.7.3",
      "rinap/rinap4:Q003362.16.9",
      "rinap/rinap4:Q003362.30.2",
      "rinap/rinap4:Q003363.5.5",
      "rinap/rinap4:Q003363.9.2",
      "rinap/rinap4:Q003363.11.8",
      "rinap/rinap4:Q003364.5.5",
      "rinap/rinap4:Q003364.9.2",
      "rinap/rinap4:Q003364.11.8",
      "rinap/rinap4:Q003365.5.2",
      "rinap/rinap4:Q003366.11.3",
      "rinap/rinap4:Q003367.3.3",
      "rinap/rinap4:Q003368.2.2",
      "rinap/rinap4:Q003368.9.1",
      "rinap/rinap4:Q003382.22.6"
    ],
    "qpn.r00002.p.s000": [
      "rinap/rinap4:Q003282.15.3"
    ],
    "qpn.r00005.p.s000": [
      "rinap/rinap4:Q003283.59.2",
      "rinap/rinap4:Q003306.8.1",
      "rinap/rinap4:Q003307.8.1",
      "rinap/rinap4:Q003308.8.1",
      "rinap/rinap4:Q003322.4.12"
    ],
    "qpn.r00007.p.s000": [
      "rinap/rinap4:Q003364.5.2",
      "rinap/rinap4:Q003364.11.1",
      "rinap/rinap4:Q003365.11.1"
    ],
    "qpn.r00006.p.s000": [
      "rinap/rinap4:Q003277.93.2",
      "rinap/rinap4:Q003280.27.5"
    ],
    "qpn.r00009.p.s000": [
      "rinap/rinap4:Q003274.48.1",
      "rinap/rinap4:Q003277.98.18",
      "rinap/rinap4:Q003289.40.2",
      "rinap/rinap4:Q003289.45.4"
    ],
    "qpn.r00008.p.s000": [
      "rinap/rinap4:Q003285.5.2"
    ],
    "qpn.r00011.p.s000": [
      "rinap/rinap4:Q003342.20.3",
      "rinap/rinap4:Q003342.24.2"
    ],
    "qpn.r00012.p.s000": [
      "rinap/rinap4:Q003362.6.6",
      "rinap/rinap4:Q003363.5.2",
      "rinap/rinap4:Q003363.11.1"
    ],
    "qpn.r00013.p.s000": [
      "rinap/rinap4:Q003280.26.3"
    ],
    "qpn.r00018.p.s000": [
      "rinap/rinap4:Q003334.250.2",
      "rinap/rinap4:Q003339.9.1",
      "rinap/rinap4:Q003345.45.1",
      "rinap/rinap4:Q003354.2.4"
    ],
    "qpn.r00019.p.s000": [
      "rinap/rinap4:Q003350.3.2",
      "rinap/rinap4:Q003351.7.1",
      "rinap/rinap4:Q003352.8.2",
      "rinap/rinap4:Q003353.6.1"
    ],
    "qpn.r0001a.p.s000": [
      "rinap/rinap4:Q003355.10.1"
    ],
    "qpn.r00016.p.s000": [
      "rinap/rinap4:Q003239.3.5",
      "rinap/rinap4:Q003272.10.2",
      "rinap/rinap4:Q003274.39.2",
      "rinap/rinap4:Q003277.36.10",
      "rinap/rinap4:Q003277.58.6",
      "rinap/rinap4:Q003278.6.3",
      "rinap/rinap4:Q003280.28.5",
      "rinap/rinap4:Q003289.37.1",
      "rinap/rinap4:Q003306.5.5",
      "rinap/rinap4:Q003307.5.5",
      "rinap/rinap4:Q003308.5.5",
      "rinap/rinap4:Q003315.4.4",
      "rinap/rinap4:Q003322.3.5",
      "rinap/rinap4:Q003333.82.2",
      "rinap/rinap4:Q003334.32.3",
      "rinap/rinap4:Q003334.109.2",
      "rinap/rinap4:Q003334.163.3",
      "rinap/rinap4:Q003334.173.1",
      "rinap/rinap4:Q003334.234.2",
      "rinap/rinap4:Q003334.318.1",
      "rinap/rinap4:Q003335.64.1",
      "rinap/rinap4:Q003339.19.2",
      "rinap/rinap4:Q003341.58.2",
      "rinap/rinap4:Q003343.15.3",
      "rinap/rinap4:Q003343.72.2",
      "rinap/rinap4:Q003343.90.1",
      "rinap/rinap4:Q003357.8.7",
      "rinap/rinap4:Q003357.9.14",
      "rinap/rinap4:Q003358.15.7",
      "rinap/rinap4:Q003358.18.2",
      "rinap/rinap4:Q003359.15.7",
      "rinap/rinap4:Q003359.18.2",
      "rinap/rinap4:Q003362.16.5",
      "rinap/rinap4:Q003362.19.2",
      "rinap/rinap4:Q003363.8.5",
      "rinap/rinap4:Q003364.8.5",
      "rinap/rinap4:Q003365.4.5"
    ],
    "qpn.r00017.p.s000": [
      "rinap/rinap4:Q003334.250.2",
      "rinap/rinap4:Q003339.9.1",
      "rinap/rinap4:Q003345.45.1",
      "rinap/rinap4:Q003350.3.2",
      "rinap/rinap4:Q003351.7.1",
      "rinap/rinap4:Q003352.8.2",
      "rinap/rinap4:Q003353.6.1",
      "rinap/rinap4:Q003354.2.4",
      "rinap/rinap4:Q003355.10.1"
    ],
    "qpn.r0001b.p.s000": [
      "rinap/rinap4:Q003277.91.15",
      "rinap/rinap4:Q003280.25.7"
    ],
    "qpn.r0001e.p.s000": [
      "rinap/rinap4:Q003283.84.3"
    ],
    "qpn.r0001c.p.s000": [
      "rinap/rinap4:Q003283.53.2",
      "rinap/rinap4:Q003363.8.9",
      "rinap/rinap4:Q003364.8.9"
    ],
    "qpn.r00015.p.s000": [
      "rinap/rinap4:Q003230.112.2",
      "rinap/rinap4:Q003246.7.5",
      "rinap/rinap4:Q003274.46.6",
      "rinap/rinap4:Q003277.92.9",
      "rinap/rinap4:Q003277.99.11",
      "rinap/rinap4:Q003293.3.2",
      "rinap/rinap4:Q003303.5.2",
      "rinap/rinap4:Q003304.9.2",
      "rinap/rinap4:Q003313.4.1",
      "rinap/rinap4:Q003314.4.4",
      "rinap/rinap4:Q003327.40.2",
      "rinap/rinap4:Q003328.11.2",
      "rinap/rinap4:Q003333.30.1",
      "rinap/rinap4:Q003333.93.4",
      "rinap/rinap4:Q003333.116.1",
      "rinap/rinap4:Q003333.139.1",
      "rinap/rinap4:Q003333.147.1",
      "rinap/rinap4:Q003333.228.2",
      "rinap/rinap4:Q003334.94.2",
      "rinap/rinap4:Q003334.135.1",
      "rinap/rinap4:Q003334.191.2",
      "rinap/rinap4:Q003334.228.2",
      "rinap/rinap4:Q003335.15.2",
      "rinap/rinap4:Q003335.22.1",
      "rinap/rinap4:Q003335.54.2",
      "rinap/rinap4:Q003335.108.1",
      "rinap/rinap4:Q003335.138.1",
      "rinap/rinap4:Q003335.163.1",
      "rinap/rinap4:Q003335.217.1",
      "rinap/rinap4:Q003338.50.1",
      "rinap/rinap4:Q003340.8.3",
      "rinap/rinap4:Q003342.9.2",
      "rinap/rinap4:Q003342.18.1",
      "rinap/rinap4:Q003345.8.3",
      "rinap/rinap4:Q003345.30.11",
      "rinap/rinap4:Q003345.35.11",
      "rinap/rinap4:Q003345.40.2",
      "rinap/rinap4:Q003347.4.2",
      "rinap/rinap4:Q003348.8.1",
      "rinap/rinap4:Q003349.6.1",
      "rinap/rinap4:Q003350.2.4",
      "rinap/rinap4:Q003351.6.1",
      "rinap/rinap4:Q003352.7.1",
      "rinap/rinap4:Q003376.8.4"
    ],
    "qpn.r00014.p.s000": [
      "rinap/rinap4:Q003230.112.2",
      "rinap/rinap4:Q003239.3.5",
      "rinap/rinap4:Q003246.7.5",
      "rinap/rinap4:Q003272.10.2",
      "rinap/rinap4:Q003274.39.2",
      "rinap/rinap4:Q003274.46.6",
      "rinap/rinap4:Q003277.36.10",
      "rinap/rinap4:Q003277.58.6",
      "rinap/rinap4:Q003277.92.9",
      "rinap/rinap4:Q003277.99.11",
      "rinap/rinap4:Q003278.6.3",
      "rinap/rinap4:Q003280.28.5",
      "rinap/rinap4:Q003289.37.1",
      "rinap/rinap4:Q003293.3.2",
      "rinap/rinap4:Q003303.5.2",
      "rinap/rinap4:Q003304.9.2",
      "rinap/rinap4:Q003306.5.5",
      "rinap/rinap4:Q003307.5.5",
      "rinap/rinap4:Q003308.5.5",
      "rinap/rinap4:Q003313.4.1",
      "rinap/rinap4:Q003314.4.4",
      "rinap/rinap4:Q003315.4.4",
      "rinap/rinap4:Q003322.3.5",
      "rinap/rinap4:Q003327.40.2",
      "rinap/rinap4:Q003328.11.2",
      "rinap/rinap4:Q003333.30.1",
      "rinap/rinap4:Q003333.82.2",
      "rinap/rinap4:Q003333.93.4",
      "rinap/rinap4:Q003333.116.1",
      "rinap/rinap4:Q003333.139.1",
      "rinap/rinap4:Q003333.147.1",
      "rinap/rinap4:Q003333.228.2",
      "rinap/rinap4:Q003334.32.3",
      "rinap/rinap4:Q003334.94.2",
      "rinap/rinap4:Q003334.109.2",
      "rinap/rinap4:Q003334.135.1",
      "rinap/rinap4:Q003334.163.3",
      "rinap/rinap4:Q003334.173.1",
      "rinap/rinap4:Q003334.191.2",
      "rinap/rinap4:Q003334.228.2",
      "rinap/rinap4:Q003334.234.2",
      "rinap/rinap4:Q003334.318.1",
      "rinap/rinap4:Q003335.15.2",
      "rinap/rinap4:Q003335.22.1",
      "rinap/rinap4:Q003335.54.2",
      "rinap/rinap4:Q003335.64.1",
      "rinap/rinap4:Q003335.108.1",
      "rinap/rinap4:Q003335.138.1",
      "rinap/rinap4:Q003335.163.1",
      "rinap/rinap4:Q003335.217.1",
      "rinap/rinap4:Q003338.50.1",
      "rinap/rinap4:Q003339.19.2",
      "rinap/rinap4:Q003340.8.3",
      "rinap/rinap4:Q003341.58.2",
      "rinap/rinap4:Q003342.9.2",
      "rinap/rinap4:Q003342.18.1",
      "rinap/rinap4:Q003343.15.3",
      "rinap/rinap4:Q003343.72.2",
      "rinap/rinap4:Q003343.90.1",
      "rinap/rinap4:Q003345.8.3",
      "rinap/rinap4:Q003345.30.11",
      "rinap/rinap4:Q003345.35.11",
      "rinap/rinap4:Q003345.40.2",
      "rinap/rinap4:Q003347.4.2",
      "rinap/rinap4:Q003348.8.1",
      "rinap/rinap4:Q003349.6.1",
      "rinap/rinap4:Q003350.2.4",
      "rinap/rinap4:Q003351.6.1",
      "rinap/rinap4:Q003352.7.1",
      "rinap/rinap4:Q003357.8.7",
      "rinap/rinap4:Q003357.9.14",
      "rinap/rinap4:Q003358.15.7",
      "rinap/rinap4:Q003358.18.2",
      "rinap/rinap4:Q003359.15.7",
      "rinap/rinap4:Q003359.18.2",
      "rinap/rinap4:Q003362.16.5",
      "rinap/rinap4:Q003362.19.2",
      "rinap/rinap4:Q003363.8.5",
      "rinap/rinap4:Q003364.8.5",
      "rinap/rinap4:Q003365.4.5",
      "rinap/rinap4:Q003376.8.4"
    ],
    "qpn.r0001d.p.s000": [
      "rinap/rinap4:Q003274.45.3",
      "rinap/rinap4:Q003277.35.8",
      "rinap/rinap4:Q003277.87.9",
      "rinap/rinap4:Q003280.17.4",
      "rinap/rinap4:Q003286.200.2",
      "rinap/rinap4:Q003286.238.2",
      "rinap/rinap4:Q003286.283.3",
      "rinap/rinap4:Q003305.6.3",
      "rinap/rinap4:Q003305.8.2",
      "rinap/rinap4:Q003305.15.5",
      "rinap/rinap4:Q003333.149.1",
      "rinap/rinap4:Q003334.175.1",
      "rinap/rinap4:Q003340.21.1",
      "rinap/rinap4:Q003387.51.3",
      "rinap/rinap4:Q003408.2.5"
    ],
    "qpn.r0001f.p.s000": [
      "rinap/rinap4:Q003230.486.2",
      "rinap/rinap4:Q003231.332.1"
    ],
    "qpn.r00020.p.s000": [
      "rinap/rinap4:Q003387.60.3"
    ],
    "qpn.r00021.p.s000": [
      "rinap/rinap4:Q003361.4.5"
    ],
    "qpn.r0000a.p.s000": [
      "rinap/rinap4:Q003286.208.1"
    ],
    "qpn.r0000b.p.s000": [
      "rinap/rinap4:Q003281.12.2",
      "rinap/rinap4:Q003289.50.4"
    ],
    "qpn.r0000c.p.s000": [
      "rinap/rinap4:Q003357.8.5",
      "rinap/rinap4:Q003358.15.5",
      "rinap/rinap4:Q003358.29.3",
      "rinap/rinap4:Q003359.15.5",
      "rinap/rinap4:Q003360.12.1"
    ],
    "qpn.r0000f.p.s000": [
      "rinap/rinap4:Q003239.6.7",
      "rinap/rinap4:Q003283.48.5",
      "rinap/rinap4:Q003407.2.4"
    ],
    "qpn.r0000d.p.s000": [
      "rinap/rinap4:Q003359.15.5"
    ],
    "qpn.r0000e.p.s000": [
      "rinap/rinap4:Q003357.8.5",
      "rinap/rinap4:Q003358.15.5",
      "rinap/rinap4:Q003358.29.3",
      "rinap/rinap4:Q003360.12.1"
    ],
    "qpn.r00010.p.s000": [
      "rinap/rinap4:Q003277.92.11"
    ]
  }
}
